[
  {
    "link_it": "https://github.com/lmbstudiocontact/cb_img_5000_it_3/raw/main/professor_cb_img_5000_it.json",
    "id_item": "professor_cb_img_5000_it",
    "id_album": "570943552",
    "english": "professor",
    "list_mean": [
      "giáo sư",
      "giảng viên"
    ],
    "cau_en": "",
    "cau_vn": "",
    "hash_code_list_mean": "303102801",
    "list_img": [
      {
        "link_thumb": "https://live.staticflickr.com/65535/51809321366_93302894b2_n.jpg",
        "link_img": "https://live.staticflickr.com/65535/51809321366_d21f1765ba_o.png",
        "id_image": "professor_4061233"
      },
      {
        "link_thumb": "https://live.staticflickr.com/65535/51809436623_e9d555aa18_n.jpg",
        "link_img": "https://live.staticflickr.com/65535/51809436623_4ac565417c_o.png",
        "id_image": "professor_4135781"
      },
      {
        "link_thumb": "https://live.staticflickr.com/65535/51808366272_48a2bef2c6_n.jpg",
        "link_img": "https://live.staticflickr.com/65535/51808366272_9ed6e89722_o.png",
        "id_image": "professor_6032237"
      }
    ],
    "hash_code_list_img": "-533152581"
  },
  {
    "link_it": "https://github.com/lmbstudiocontact/cb_img_5000_it_0/raw/main/canister_cb_img_5000_it.json",
    "id_item": "canister_cb_img_5000_it",
    "id_album": "570943552",
    "english": "canister",
    "list_mean": [
      "hộp nhỏ"
    ],
    "cau_en": "",
    "cau_vn": "",
    "hash_code_list_mean": "661712883",
    "list_img": [
      {
        "link_thumb": "https://live.staticflickr.com/65535/51809686219_5d5d3a47ed_n.jpg",
        "link_img": "https://live.staticflickr.com/65535/51809686219_b718d89f71_o.png",
        "id_image": "canister_270313"
      },
      {
        "link_thumb": "https://live.staticflickr.com/65535/51808375837_e963baa62e_n.jpg",
        "link_img": "https://live.staticflickr.com/65535/51808375837_75c9f732b9_o.png",
        "id_image": "canister_3654856"
      },
      {
        "link_thumb": "https://live.staticflickr.com/65535/51809446083_46d20b9e37_n.jpg",
        "link_img": "https://live.staticflickr.com/65535/51809446083_84209ef688_o.png",
        "id_image": "canister_4636906"
      },
      {
        "link_thumb": "https://live.staticflickr.com/65535/51809446038_bc3d63a5b3_n.jpg",
        "link_img": "https://live.staticflickr.com/65535/51809446038_ecfca9eb53_o.png",
        "id_image": "canister_4805774"
      },
      {
        "link_thumb": "https://live.staticflickr.com/65535/51809686084_28a5e08909_n.jpg",
        "link_img": "https://live.staticflickr.com/65535/51809686084_214ac1d5f2_o.png",
        "id_image": "canister_6255508"
      }
    ],
    "hash_code_list_img": "788523385"
  },
  {
    "link_it": "https://github.com/lmbstudiocontact/cb_img_5000_it_5/raw/main/wrinkle_cb_img_5000_it.json",
    "id_item": "wrinkle_cb_img_5000_it",
    "id_album": "570943552",
    "english": "wrinkle",
    "list_mean": [
      "vết nhăn",
      "xuất hiện vết nhăn"
    ],
    "cau_en": "",
    "cau_vn": "",
    "hash_code_list_mean": "360950245",
    "list_img": [
      {
        "link_thumb": "https://live.staticflickr.com/65535/51808377197_000d562e4e_n.jpg",
        "link_img": "https://live.staticflickr.com/65535/51808377197_56a5c1f264_o.png",
        "id_image": "wrinkle_4236621"
      },
      {
        "link_thumb": "https://live.staticflickr.com/65535/51809687374_9aff2bd011_n.jpg",
        "link_img": "https://live.staticflickr.com/65535/51809687374_da45022707_o.png",
        "id_image": "wrinkle_4675614"
      },
      {
        "link_thumb": "https://live.staticflickr.com/65535/51809332381_26f84efb09_n.jpg",
        "link_img": "https://live.staticflickr.com/65535/51809332381_0d3a6964f2_o.png",
        "id_image": "wrinkle_5220715"
      }
    ],
    "hash_code_list_img": "1279446823"
  },
  {
    "link_it": "https://github.com/lmbstudiocontact/cb_img_5000_it_5/raw/main/worm_cb_img_5000_it.json",
    "id_item": "worm_cb_img_5000_it",
    "id_album": "570943552",
    "english": "worm",
    "list_mean": [
      "con giun",
      "luồn vào",
      "moi tin"
    ],
    "cau_en": "",
    "cau_vn": "",
    "hash_code_list_mean": "1507098223",
    "list_img": [
      {
        "link_thumb": "https://live.staticflickr.com/65535/51809448538_7c4447aa7d_n.jpg",
        "link_img": "https://live.staticflickr.com/65535/51809448538_2277304dd7_o.png",
        "id_image": "worm_2959415"
      },
      {
        "link_thumb": "https://live.staticflickr.com/65535/51809688509_d045f31463_n.jpg",
        "link_img": "https://live.staticflickr.com/65535/51809688509_af487034f7_o.png",
        "id_image": "worm_350973"
      }
    ],
    "hash_code_list_img": "-850352358"
  },
  {
    "link_it": "https://github.com/lmbstudiocontact/cb_img_5000_it_3/raw/main/papacy_cb_img_5000_it.json",
    "id_item": "papacy_cb_img_5000_it",
    "id_album": "570943552",
    "english": "papacy",
    "list_mean": [
      "chức giáo hoàng",
      "chế độ giáo hoàng"
    ],
    "cau_en": "",
    "cau_vn": "",
    "hash_code_list_mean": "-73990222",
    "list_img": [
      {
        "link_thumb": "https://live.staticflickr.com/65535/51809449433_afc03ff806_n.jpg",
        "link_img": "https://live.staticflickr.com/65535/51809449433_1fe692afed_o.png",
        "id_image": "papacy_280016"
      }
    ],
    "hash_code_list_img": "558108245"
  },
  {
    "link_it": "https://github.com/lmbstudiocontact/cb_img_5000_it_0/raw/main/cash_cb_img_5000_it.json",
    "id_item": "cash_cb_img_5000_it",
    "id_album": "570943552",
    "english": "cash",
    "list_mean": [
      "tiền mặt",
      "sự thanh toán bằng tiền mặt",
      "tiền",
      "đổi séc sang tiền mặt"
    ],
    "cau_en": "",
    "cau_vn": "",
    "hash_code_list_mean": "-1518664079",
    "list_img": [
      {
        "link_thumb": "https://live.staticflickr.com/65535/51809437508_b676e4c0c1_n.jpg",
        "link_img": "https://live.staticflickr.com/65535/51809437508_349f3b7b83_o.png",
        "id_image": "cash_3898031"
      },
      {
        "link_thumb": "https://live.staticflickr.com/65535/51809322221_1908ea980b_n.jpg",
        "link_img": "https://live.staticflickr.com/65535/51809322221_0151294146_o.png",
        "id_image": "cash_3937098"
      },
      {
        "link_thumb": "https://live.staticflickr.com/65535/51810058985_9f482411e4_n.jpg",
        "link_img": "https://live.staticflickr.com/65535/51810058985_ff8ce2dff3_o.png",
        "id_image": "cash_4564940"
      }
    ],
    "hash_code_list_img": "255604176"
  },
  {
    "link_it": "https://github.com/lmbstudiocontact/cb_img_5000_it_4/raw/main/speaker_cb_img_5000_it.json",
    "id_item": "speaker_cb_img_5000_it",
    "id_album": "570943552",
    "english": "speaker",
    "list_mean": [
      "người nói",
      "loa phóng thanh"
    ],
    "cau_en": "",
    "cau_vn": "",
    "hash_code_list_mean": "-1158959149",
    "list_img": [
      {
        "link_thumb": "https://live.staticflickr.com/65535/51809679944_e1fb818295_n.jpg",
        "link_img": "https://live.staticflickr.com/65535/51809679944_8632aeeec4_o.png",
        "id_image": "speaker_422509"
      }
    ],
    "hash_code_list_img": "1368297824"
  },
  {
    "link_it": "https://github.com/lmbstudiocontact/cb_img_5000_it_2/raw/main/lunar_cb_img_5000_it.json",
    "id_item": "lunar_cb_img_5000_it",
    "id_album": "570943552",
    "english": "lunar",
    "list_mean": [
      "mặt trăng"
    ],
    "cau_en": "",
    "cau_vn": "",
    "hash_code_list_mean": "-68896505",
    "list_img": [
      {
        "link_thumb": "https://live.staticflickr.com/65535/51809332626_3ec98f57d4_n.jpg",
        "link_img": "https://live.staticflickr.com/65535/51809332626_98d59e7d42_o.png",
        "id_image": "lunar_1469374"
      },
      {
        "link_thumb": "https://live.staticflickr.com/65535/51808377407_6f6c991969_n.jpg",
        "link_img": "https://live.staticflickr.com/65535/51808377407_2d0fd3926a_o.png",
        "id_image": "lunar_1469375"
      },
      {
        "link_thumb": "https://live.staticflickr.com/65535/51808377382_1fbde0cfc9_n.jpg",
        "link_img": "https://live.staticflickr.com/65535/51808377382_4108a27e1e_o.png",
        "id_image": "lunar_2984103"
      },
      {
        "link_thumb": "https://live.staticflickr.com/65535/51809447568_2e96d44830_n.jpg",
        "link_img": "https://live.staticflickr.com/65535/51809447568_60c8649188_o.png",
        "id_image": "lunar_4383590"
      },
      {
        "link_thumb": "https://live.staticflickr.com/65535/51809447533_8e77ef98f1_n.jpg",
        "link_img": "https://live.staticflickr.com/65535/51809447533_d9ab131ed7_o.png",
        "id_image": "lunar_4657808"
      }
    ],
    "hash_code_list_img": "-795908569"
  },
  {
    "link_it": "https://github.com/lmbstudiocontact/cb_img_5000_it_5/raw/main/volume_cb_img_5000_it.json",
    "id_item": "volume_cb_img_5000_it",
    "id_album": "570943552",
    "english": "volume",
    "list_mean": [
      "quyển, cuốn sách",
      "tập",
      "dung tích, thể tích",
      "khối lượng, số lượng",
      "âm lượng"
    ],
    "cau_en": "",
    "cau_vn": "",
    "hash_code_list_mean": "1185980347",
    "list_img": [
      {
        "link_thumb": "https://live.staticflickr.com/65535/51809455648_a4f746b03a_n.jpg",
        "link_img": "https://live.staticflickr.com/65535/51809455648_70cbfa361d_o.png",
        "id_image": "volume_227193"
      },
      {
        "link_thumb": "https://live.staticflickr.com/65535/51808385677_16eb7ae227_n.jpg",
        "link_img": "https://live.staticflickr.com/65535/51808385677_8f07bb3f92_o.png",
        "id_image": "volume_227194"
      },
      {
        "link_thumb": "https://live.staticflickr.com/65535/51809340716_eeb3403a8a_n.jpg",
        "link_img": "https://live.staticflickr.com/65535/51809340716_5434b61cdb_o.png",
        "id_image": "volume_227196"
      }
    ],
    "hash_code_list_img": "1221928777"
  },
  {
    "link_it": "https://github.com/lmbstudiocontact/cb_img_5000_it_3/raw/main/pedal_cb_img_5000_it.json",
    "id_item": "pedal_cb_img_5000_it",
    "id_album": "570943552",
    "english": "pedal",
    "list_mean": [
      "bàn đạp",
      "đạp"
    ],
    "cau_en": "",
    "cau_vn": "",
    "hash_code_list_mean": "-870979983",
    "list_img": [
      {
        "link_thumb": "https://live.staticflickr.com/65535/51808369177_70c1682d3a_n.jpg",
        "link_img": "https://live.staticflickr.com/65535/51808369177_d2d7e3013f_o.png",
        "id_image": "pedal_1924264"
      },
      {
        "link_thumb": "https://live.staticflickr.com/65535/51809439328_808d53845d_n.jpg",
        "link_img": "https://live.staticflickr.com/65535/51809439328_2d496076ed_o.png",
        "id_image": "pedal_5349649"
      },
      {
        "link_thumb": "https://live.staticflickr.com/65535/51808369247_40ca7b2266_n.jpg",
        "link_img": "https://live.staticflickr.com/65535/51808369247_6e2e1532c2_o.png",
        "id_image": "pedal_637954"
      }
    ],
    "hash_code_list_img": "2094544870"
  },
  {
    "link_it": "https://github.com/lmbstudiocontact/cb_img_5000_it_4/raw/main/send_cb_img_5000_it.json",
    "id_item": "send_cb_img_5000_it",
    "id_album": "570943552",
    "english": "send",
    "list_mean": [
      "gửi; phái",
      "bắn ra",
      "đẩy tới"
    ],
    "cau_en": "",
    "cau_vn": "",
    "hash_code_list_mean": "848155740",
    "list_img": [
      {
        "link_thumb": "https://live.staticflickr.com/65535/51809350241_a17b9cd11e_n.jpg",
        "link_img": "https://live.staticflickr.com/65535/51809350241_7832227d11_o.png",
        "id_image": "send_1674944"
      },
      {
        "link_thumb": "https://live.staticflickr.com/65535/51808394987_f3484e8832_n.jpg",
        "link_img": "https://live.staticflickr.com/65535/51808394987_c254d9cce4_o.png",
        "id_image": "send_3893142"
      },
      {
        "link_thumb": "https://live.staticflickr.com/65535/51810087425_e2fbdf04d4_n.jpg",
        "link_img": "https://live.staticflickr.com/65535/51810087425_98c1ed7f97_o.png",
        "id_image": "send_4313102"
      },
      {
        "link_thumb": "https://live.staticflickr.com/65535/51809350256_f15c2558ba_n.jpg",
        "link_img": "https://live.staticflickr.com/65535/51809350256_2031b62793_o.png",
        "id_image": "send_928908"
      }
    ],
    "hash_code_list_img": "-1325786947"
  },
  {
    "link_it": "https://github.com/lmbstudiocontact/cb_img_5000_it_2/raw/main/host_cb_img_5000_it.json",
    "id_item": "host_cb_img_5000_it",
    "id_album": "570943552",
    "english": "host",
    "list_mean": [
      "chủ nhà",
      "động vật hoặc thực vật mà vật ký sinh sống bám vào",
      "rất đông; vô số"
    ],
    "cau_en": "",
    "cau_vn": "",
    "hash_code_list_mean": "-1118865795",
    "list_img": [
      {
        "link_thumb": "https://live.staticflickr.com/65535/51808375352_d022a2c0e2_n.jpg",
        "link_img": "https://live.staticflickr.com/65535/51808375352_8f8e62db38_o.png",
        "id_image": "host_2162279"
      },
      {
        "link_thumb": "https://live.staticflickr.com/65535/51809330621_00a85a37b0_n.jpg",
        "link_img": "https://live.staticflickr.com/65535/51809330621_c2d76f0a25_o.png",
        "id_image": "host_4799517"
      },
      {
        "link_thumb": "https://live.staticflickr.com/65535/51810067400_f94b1a6620_n.jpg",
        "link_img": "https://live.staticflickr.com/65535/51810067400_6aa68e927e_o.png",
        "id_image": "host_6036772"
      },
      {
        "link_thumb": "https://live.staticflickr.com/65535/51809685769_b72745230c_n.jpg",
        "link_img": "https://live.staticflickr.com/65535/51809685769_010320a963_o.png",
        "id_image": "host_860259"
      }
    ],
    "hash_code_list_img": "1038502707"
  },
  {
    "link_it": "https://github.com/lmbstudiocontact/cb_img_5000_it_1/raw/main/concrete_cb_img_5000_it.json",
    "id_item": "concrete_cb_img_5000_it",
    "id_album": "570943552",
    "english": "concrete",
    "list_mean": [
      "cụ thể",
      "xác định cụ thể",
      "bê tông",
      "phủ bê tông"
    ],
    "cau_en": "",
    "cau_vn": "",
    "hash_code_list_mean": "1066501270",
    "list_img": [
      {
        "link_thumb": "https://live.staticflickr.com/65535/51808357527_4c898a1287_n.jpg",
        "link_img": "https://live.staticflickr.com/65535/51808357527_2114300cb1_o.png",
        "id_image": "concrete_1563143"
      },
      {
        "link_thumb": "https://live.staticflickr.com/65535/51809428273_fe66664194_n.jpg",
        "link_img": "https://live.staticflickr.com/65535/51809428273_5259d69b42_o.png",
        "id_image": "concrete_4631742"
      },
      {
        "link_thumb": "https://live.staticflickr.com/65535/51809313461_e8c1ceebb6_n.jpg",
        "link_img": "https://live.staticflickr.com/65535/51809313461_2b320c1742_o.png",
        "id_image": "concrete_4631803"
      }
    ],
    "hash_code_list_img": "-334729599"
  },
  {
    "link_it": "https://github.com/lmbstudiocontact/cb_img_5000_it_4/raw/main/sofa_cb_img_5000_it.json",
    "id_item": "sofa_cb_img_5000_it",
    "id_album": "570943552",
    "english": "sofa",
    "list_mean": [
      "ghế xôfa"
    ],
    "cau_en": "",
    "cau_vn": "",
    "hash_code_list_mean": "-1032946120",
    "list_img": [
      {
        "link_thumb": "https://live.staticflickr.com/65535/51809327106_d47101a2ef_n.jpg",
        "link_img": "https://live.staticflickr.com/65535/51809327106_f48d7bf6c2_o.png",
        "id_image": "sofa_603393"
      }
    ],
    "hash_code_list_img": "565205673"
  },
  {
    "link_it": "https://github.com/lmbstudiocontact/cb_img_5000_it_2/raw/main/hurricane_cb_img_5000_it.json",
    "id_item": "hurricane_cb_img_5000_it",
    "id_album": "570943552",
    "english": "hurricane",
    "list_mean": [
      "bão"
    ],
    "cau_en": "",
    "cau_vn": "",
    "hash_code_list_mean": "101357",
    "list_img": [
      {
        "link_thumb": "https://live.staticflickr.com/65535/51809441908_edefb440b9_n.jpg",
        "link_img": "https://live.staticflickr.com/65535/51809441908_648f8d8ebc_o.png",
        "id_image": "hurricane_2237892"
      },
      {
        "link_thumb": "https://live.staticflickr.com/65535/51809441868_5d3101c510_n.jpg",
        "link_img": "https://live.staticflickr.com/65535/51809441868_33d5278abb_o.png",
        "id_image": "hurricane_3436812"
      },
      {
        "link_thumb": "https://live.staticflickr.com/65535/51808371662_65f0fc5fe2_n.jpg",
        "link_img": "https://live.staticflickr.com/65535/51808371662_4c4a0718fd_o.png",
        "id_image": "hurricane_491243"
      },
      {
        "link_thumb": "https://live.staticflickr.com/65535/51810063805_e7c2ed233e_n.jpg",
        "link_img": "https://live.staticflickr.com/65535/51810063805_3015cf9592_o.png",
        "id_image": "hurricane_798347"
      }
    ],
    "hash_code_list_img": "1215652558"
  },
  {
    "link_it": "https://github.com/lmbstudiocontact/cb_img_5000_it_4/raw/main/turnstile_cb_img_5000_it.json",
    "id_item": "turnstile_cb_img_5000_it",
    "id_album": "570943552",
    "english": "turnstile",
    "list_mean": [
      "cửa quay"
    ],
    "cau_en": "",
    "cau_vn": "",
    "hash_code_list_mean": "-945227452",
    "list_img": [
      {
        "link_thumb": "https://live.staticflickr.com/65535/51809443178_8768c32e97_n.jpg",
        "link_img": "https://live.staticflickr.com/65535/51809443178_a18a369812_o.png",
        "id_image": "turnstile_3124255"
      }
    ],
    "hash_code_list_img": "215955508"
  },
  {
    "link_it": "https://github.com/lmbstudiocontact/cb_img_5000_it_1/raw/main/deadlock_cb_img_5000_it.json",
    "id_item": "deadlock_cb_img_5000_it",
    "id_album": "570943552",
    "english": "deadlock",
    "list_mean": [
      "sự bế tắc"
    ],
    "cau_en": "",
    "cau_vn": "",
    "hash_code_list_mean": "-1101647706",
    "list_img": [
      {
        "link_thumb": "https://live.staticflickr.com/65535/51810045690_a0c59da3a5_n.jpg",
        "link_img": "https://live.staticflickr.com/65535/51810045690_dc6d293e5e_o.png",
        "id_image": "deadlock_311573"
      }
    ],
    "hash_code_list_img": "1009913002"
  },
  {
    "link_it": "https://github.com/lmbstudiocontact/cb_img_5000_it_4/raw/main/socket_cb_img_5000_it.json",
    "id_item": "socket_cb_img_5000_it",
    "id_album": "570943552",
    "english": "socket",
    "list_mean": [
      "lỗ, hốc, ổ"
    ],
    "cau_en": "",
    "cau_vn": "",
    "hash_code_list_mean": "1960462085",
    "list_img": [
      {
        "link_thumb": "https://live.staticflickr.com/65535/51809327391_b78250b778_n.jpg",
        "link_img": "https://live.staticflickr.com/65535/51809327391_15dc395e38_o.png",
        "id_image": "socket_252598"
      },
      {
        "link_thumb": "https://live.staticflickr.com/65535/51809327336_6aed82dc1a_n.jpg",
        "link_img": "https://live.staticflickr.com/65535/51809327336_8219272542_o.png",
        "id_image": "socket_403151"
      }
    ],
    "hash_code_list_img": "2070052087"
  },
  {
    "link_it": "https://github.com/lmbstudiocontact/cb_img_5000_it_3/raw/main/pauper_cb_img_5000_it.json",
    "id_item": "pauper_cb_img_5000_it",
    "id_album": "570943552",
    "english": "pauper",
    "list_mean": [
      "người cùng khổ"
    ],
    "cau_en": "",
    "cau_vn": "",
    "hash_code_list_mean": "1917735875",
    "list_img": [
      {
        "link_thumb": "https://live.staticflickr.com/65535/51809682124_c299cfb50b_n.jpg",
        "link_img": "https://live.staticflickr.com/65535/51809682124_3061d0b44c_o.png",
        "id_image": "pauper_1396219"
      }
    ],
    "hash_code_list_img": "1365604443"
  },
  {
    "link_it": "https://github.com/lmbstudiocontact/cb_img_5000_it_4/raw/main/snooze_cb_img_5000_it.json",
    "id_item": "snooze_cb_img_5000_it",
    "id_album": "570943552",
    "english": "snooze",
    "list_mean": [
      "ngủ gà ngủ gật",
      "một giấc ngủ ngắn"
    ],
    "cau_en": "",
    "cau_vn": "",
    "hash_code_list_mean": "81118956",
    "list_img": [
      {
        "link_thumb": "https://live.staticflickr.com/65535/51809684259_8558fe567e_n.jpg",
        "link_img": "https://live.staticflickr.com/65535/51809684259_516bcda150_o.png",
        "id_image": "snooze_3602457"
      }
    ],
    "hash_code_list_img": "2099208430"
  },
  {
    "link_it": "https://github.com/lmbstudiocontact/cb_img_5000_it_4/raw/main/summertime_cb_img_5000_it.json",
    "id_item": "summertime_cb_img_5000_it",
    "id_album": "570943552",
    "english": "summertime",
    "list_mean": [
      "mùa hạ"
    ],
    "cau_en": "",
    "cau_vn": "",
    "hash_code_list_mean": "-941501533",
    "list_img": [
      {
        "link_thumb": "https://live.staticflickr.com/65535/51809337951_018187da6e_n.jpg",
        "link_img": "https://live.staticflickr.com/65535/51809337951_ca36ff1ecd_o.png",
        "id_image": "summertime_306713"
      },
      {
        "link_thumb": "https://live.staticflickr.com/65535/51809452818_454defc269_n.jpg",
        "link_img": "https://live.staticflickr.com/65535/51809452818_7d20e2634a_o.png",
        "id_image": "summertime_3579891"
      }
    ],
    "hash_code_list_img": "-117275411"
  },
  {
    "link_it": "https://github.com/lmbstudiocontact/cb_img_5000_it_2/raw/main/knot_cb_img_5000_it.json",
    "id_item": "knot_cb_img_5000_it",
    "id_album": "570943552",
    "english": "knot",
    "list_mean": [
      "nút",
      "mắt gỗ",
      "nhóm",
      "hải lý",
      "thắt nút"
    ],
    "cau_en": "",
    "cau_vn": "",
    "hash_code_list_mean": "-1235282981",
    "list_img": [
      {
        "link_thumb": "https://live.staticflickr.com/65535/51810061845_c5e3f150aa_n.jpg",
        "link_img": "https://live.staticflickr.com/65535/51810061845_f1ffa15ec2_o.png",
        "id_image": "knot_2485126"
      },
      {
        "link_thumb": "https://live.staticflickr.com/65535/51809324951_7c906f45f7_n.jpg",
        "link_img": "https://live.staticflickr.com/65535/51809324951_6d097cf8e0_o.png",
        "id_image": "knot_2485183"
      },
      {
        "link_thumb": "https://live.staticflickr.com/65535/51809440033_5c309f4ee2_n.jpg",
        "link_img": "https://live.staticflickr.com/65535/51809440033_2d9b2628e7_o.png",
        "id_image": "knot_486366"
      }
    ],
    "hash_code_list_img": "790311943"
  },
  {
    "link_it": "https://github.com/lmbstudiocontact/cb_img_5000_it_1/raw/main/couple_cb_img_5000_it.json",
    "id_item": "couple_cb_img_5000_it",
    "id_album": "570943552",
    "english": "couple",
    "list_mean": [
      "hai",
      "đôi; cặp",
      "kết hợp"
    ],
    "cau_en": "",
    "cau_vn": "",
    "hash_code_list_mean": "-654194509",
    "list_img": [
      {
        "link_thumb": "https://live.staticflickr.com/65535/51809682139_e262679884_n.jpg",
        "link_img": "https://live.staticflickr.com/65535/51809682139_15d1a4e5a9_o.png",
        "id_image": "couple_332952"
      }
    ],
    "hash_code_list_img": "940097051"
  },
  {
    "link_it": "https://github.com/lmbstudiocontact/cb_img_5000_it_4/raw/main/stair_cb_img_5000_it.json",
    "id_item": "stair_cb_img_5000_it",
    "id_album": "570943552",
    "english": "stair",
    "list_mean": [
      "bậc thang"
    ],
    "cau_en": "",
    "cau_vn": "",
    "hash_code_list_mean": "181884957",
    "list_img": [
      {
        "link_thumb": "https://live.staticflickr.com/65535/51809350421_81066abcc6_n.jpg",
        "link_img": "https://live.staticflickr.com/65535/51809350421_7c14352131_o.png",
        "id_image": "stair_1533284"
      },
      {
        "link_thumb": "https://live.staticflickr.com/65535/51809704939_4f351c4c91_n.jpg",
        "link_img": "https://live.staticflickr.com/65535/51809704939_94b1113c17_o.png",
        "id_image": "stair_5798480"
      },
      {
        "link_thumb": "https://live.staticflickr.com/65535/51810087555_9d632d00ac_n.jpg",
        "link_img": "https://live.staticflickr.com/65535/51810087555_3bb40c5560_o.png",
        "id_image": "stair_6342781"
      }
    ],
    "hash_code_list_img": "-29349790"
  },
  {
    "link_it": "https://github.com/lmbstudiocontact/cb_img_5000_it_1/raw/main/doll_cb_img_5000_it.json",
    "id_item": "doll_cb_img_5000_it",
    "id_album": "570943552",
    "english": "doll",
    "list_mean": [
      "búp bê"
    ],
    "cau_en": "",
    "cau_vn": "",
    "hash_code_list_mean": "-1255059601",
    "list_img": [
      {
        "link_thumb": "https://live.staticflickr.com/65535/51808355457_5d61b59e45_n.jpg",
        "link_img": "https://live.staticflickr.com/65535/51808355457_f870cf27d4_o.png",
        "id_image": "doll_3898306"
      },
      {
        "link_thumb": "https://live.staticflickr.com/65535/51809666304_b571eb4c12_n.jpg",
        "link_img": "https://live.staticflickr.com/65535/51809666304_f271d93cbf_o.png",
        "id_image": "doll_3957269"
      },
      {
        "link_thumb": "https://live.staticflickr.com/65535/51809311251_13baecf85b_n.jpg",
        "link_img": "https://live.staticflickr.com/65535/51809311251_c123752b9f_o.png",
        "id_image": "doll_5884229"
      }
    ],
    "hash_code_list_img": "-703788939"
  },
  {
    "link_it": "https://github.com/lmbstudiocontact/cb_img_5000_it_3/raw/main/neck_cb_img_5000_it.json",
    "id_item": "neck_cb_img_5000_it",
    "id_album": "570943552",
    "english": "neck",
    "list_mean": [
      "cổ",
      "cổ áo",
      "phần cổ",
      "ôm ấp"
    ],
    "cau_en": "",
    "cau_vn": "",
    "hash_code_list_mean": "2042716298",
    "list_img": [
      {
        "link_thumb": "https://live.staticflickr.com/65535/51810063540_1a3f03d384_n.jpg",
        "link_img": "https://live.staticflickr.com/65535/51810063540_581326b8fc_o.png",
        "id_image": "neck_2688254"
      },
      {
        "link_thumb": "https://live.staticflickr.com/65535/51809441608_50fd5efe0d_n.jpg",
        "link_img": "https://live.staticflickr.com/65535/51809441608_ba9e48a49a_o.png",
        "id_image": "neck_2688307"
      },
      {
        "link_thumb": "https://live.staticflickr.com/65535/51809681649_89e7109298_n.jpg",
        "link_img": "https://live.staticflickr.com/65535/51809681649_e560612ae7_o.png",
        "id_image": "neck_5737469"
      }
    ],
    "hash_code_list_img": "-1834628188"
  },
  {
    "link_it": "https://github.com/lmbstudiocontact/cb_img_5000_it_4/raw/main/seductive_cb_img_5000_it.json",
    "id_item": "seductive_cb_img_5000_it",
    "id_album": "570943552",
    "english": "seductive",
    "list_mean": [
      "có sức quyến rũ"
    ],
    "cau_en": "",
    "cau_vn": "",
    "hash_code_list_mean": "1143732085",
    "list_img": [
      {
        "link_thumb": "https://live.staticflickr.com/65535/51809438388_4b2349abea_n.jpg",
        "link_img": "https://live.staticflickr.com/65535/51809438388_92da8c7702_o.png",
        "id_image": "seductive_339960"
      }
    ],
    "hash_code_list_img": "975791714"
  },
  {
    "link_it": "https://github.com/lmbstudiocontact/cb_img_5000_it_4/raw/main/umpire_cb_img_5000_it.json",
    "id_item": "umpire_cb_img_5000_it",
    "id_album": "570943552",
    "english": "umpire",
    "list_mean": [
      "trọng tài",
      "làm trọng tài"
    ],
    "cau_en": "",
    "cau_vn": "",
    "hash_code_list_mean": "-1974644230",
    "list_img": [
      {
        "link_thumb": "https://live.staticflickr.com/65535/51809354276_010703bcaa_n.jpg",
        "link_img": "https://live.staticflickr.com/65535/51809354276_7304550ff1_o.png",
        "id_image": "umpire_6308728"
      }
    ],
    "hash_code_list_img": "876835657"
  },
  {
    "link_it": "https://github.com/lmbstudiocontact/cb_img_5000_it_0/raw/main/agenda_cb_img_5000_it.json",
    "id_item": "agenda_cb_img_5000_it",
    "id_album": "570943552",
    "english": "agenda",
    "list_mean": [
      "chương trình hội nghị"
    ],
    "cau_en": "",
    "cau_vn": "",
    "hash_code_list_mean": "35923628",
    "list_img": [
      {
        "link_thumb": "https://live.staticflickr.com/65535/51809434073_33e6e96be8_n.jpg",
        "link_img": "https://live.staticflickr.com/65535/51809434073_799974b772_o.png",
        "id_image": "agenda_392776"
      },
      {
        "link_thumb": "https://live.staticflickr.com/65535/51809318821_fc9b010dbf_n.jpg",
        "link_img": "https://live.staticflickr.com/65535/51809318821_8179af058a_o.png",
        "id_image": "agenda_419277"
      },
      {
        "link_thumb": "https://live.staticflickr.com/65535/51808363357_4bfe1a9240_n.jpg",
        "link_img": "https://live.staticflickr.com/65535/51808363357_90884f3170_o.png",
        "id_image": "agenda_494719"
      },
      {
        "link_thumb": "https://live.staticflickr.com/65535/51809318751_5b66407500_n.jpg",
        "link_img": "https://live.staticflickr.com/65535/51809318751_b99484794f_o.png",
        "id_image": "agenda_735185"
      }
    ],
    "hash_code_list_img": "-1442365049"
  },
  {
    "link_it": "https://github.com/lmbstudiocontact/cb_img_5000_it_4/raw/main/talk_cb_img_5000_it.json",
    "id_item": "talk_cb_img_5000_it",
    "id_album": "570943552",
    "english": "talk",
    "list_mean": [
      "nói chuyện",
      "tán chuyện",
      "nói về, bàn bạc về",
      "hội đàm",
      "bài giảng",
      "lời bàn tán",
      "chuyện gẫu"
    ],
    "cau_en": "",
    "cau_vn": "",
    "hash_code_list_mean": "1463970517",
    "list_img": [
      {
        "link_thumb": "https://live.staticflickr.com/65535/51809327246_cd053bfb85_n.jpg",
        "link_img": "https://live.staticflickr.com/65535/51809327246_ffc0ba59af_o.png",
        "id_image": "talk_1376427"
      },
      {
        "link_thumb": "https://live.staticflickr.com/65535/51810064045_5c5a3af526_n.jpg",
        "link_img": "https://live.staticflickr.com/65535/51810064045_5ab1dbcc19_o.png",
        "id_image": "talk_2542449"
      },
      {
        "link_thumb": "https://live.staticflickr.com/65535/51809682334_1266eed92f_n.jpg",
        "link_img": "https://live.staticflickr.com/65535/51809682334_eaa99c88d7_o.png",
        "id_image": "talk_3890870"
      }
    ],
    "hash_code_list_img": "-1658020232"
  },
  {
    "link_it": "https://github.com/lmbstudiocontact/cb_img_5000_it_2/raw/main/hit_cb_img_5000_it.json",
    "id_item": "hit_cb_img_5000_it",
    "id_album": "570943552",
    "english": "hit",
    "list_mean": [
      "đánh, đấm, nện",
      "đâm, đụng",
      "làm tổn thương, làm đau khổ",
      "tìm ra, vớ được",
      "cú đánh; đòn",
      "điểm ghi được",
      "việc thành công"
    ],
    "cau_en": "",
    "cau_vn": "",
    "hash_code_list_mean": "1344248411",
    "list_img": [
      {
        "link_thumb": "https://live.staticflickr.com/65535/51809691254_256b4415aa_n.jpg",
        "link_img": "https://live.staticflickr.com/65535/51809691254_20c473c9bc_o.png",
        "id_image": "hit_1477178"
      }
    ],
    "hash_code_list_img": "639651758"
  },
  {
    "link_it": "https://github.com/lmbstudiocontact/cb_img_5000_it_2/raw/main/kite_cb_img_5000_it.json",
    "id_item": "kite_cb_img_5000_it",
    "id_album": "570943552",
    "english": "kite",
    "list_mean": [
      "cái diều"
    ],
    "cau_en": "",
    "cau_vn": "",
    "hash_code_list_mean": "1603334381",
    "list_img": [
      {
        "link_thumb": "https://live.staticflickr.com/65535/51809681394_26b4ce0fea_n.jpg",
        "link_img": "https://live.staticflickr.com/65535/51809681394_032c2bde07_o.png",
        "id_image": "kite_5333217"
      }
    ],
    "hash_code_list_img": "337245986"
  },
  {
    "link_it": "https://github.com/lmbstudiocontact/cb_img_5000_it_3/raw/main/physics_cb_img_5000_it.json",
    "id_item": "physics_cb_img_5000_it",
    "id_album": "570943552",
    "english": "physics",
    "list_mean": [
      "môn vật lý"
    ],
    "cau_en": "",
    "cau_vn": "",
    "hash_code_list_mean": "232767980",
    "list_img": [
      {
        "link_thumb": "https://live.staticflickr.com/65535/51809703654_cd3418909d_n.jpg",
        "link_img": "https://live.staticflickr.com/65535/51809703654_b2b2e82842_o.png",
        "id_image": "physics_195821"
      },
      {
        "link_thumb": "https://live.staticflickr.com/65535/51809703624_000557d084_n.jpg",
        "link_img": "https://live.staticflickr.com/65535/51809703624_0d89f823bb_o.png",
        "id_image": "physics_2161370"
      },
      {
        "link_thumb": "https://live.staticflickr.com/65535/51810086145_fbbd3e34be_n.jpg",
        "link_img": "https://live.staticflickr.com/65535/51810086145_3ef4e33c74_o.png",
        "id_image": "physics_4819810"
      },
      {
        "link_thumb": "https://live.staticflickr.com/65535/51810086130_ec8843721b_n.jpg",
        "link_img": "https://live.staticflickr.com/65535/51810086130_59f975c95a_o.png",
        "id_image": "physics_5190400"
      }
    ],
    "hash_code_list_img": "-760342960"
  },
  {
    "link_it": "https://github.com/lmbstudiocontact/cb_img_5000_it_2/raw/main/inbox_cb_img_5000_it.json",
    "id_item": "inbox_cb_img_5000_it",
    "id_album": "570943552",
    "english": "inbox",
    "list_mean": [
      "hòm thư",
      "khay tài liệu"
    ],
    "cau_en": "",
    "cau_vn": "",
    "hash_code_list_mean": "1016410331",
    "list_img": [
      {
        "link_thumb": "https://live.staticflickr.com/65535/51809320046_eb4ebab9fa_n.jpg",
        "link_img": "https://live.staticflickr.com/65535/51809320046_fde0486d60_o.png",
        "id_image": "inbox_179875"
      },
      {
        "link_thumb": "https://live.staticflickr.com/65535/51808364667_cc0710d643_n.jpg",
        "link_img": "https://live.staticflickr.com/65535/51808364667_0131cc81f8_o.png",
        "id_image": "inbox_3188172"
      },
      {
        "link_thumb": "https://live.staticflickr.com/65535/51808364772_1343c1ae36_n.jpg",
        "link_img": "https://live.staticflickr.com/65535/51808364772_69dc7733bf_o.png",
        "id_image": "inbox_547044"
      },
      {
        "link_thumb": "https://live.staticflickr.com/65535/51808364707_b64e9cc6a8_n.jpg",
        "link_img": "https://live.staticflickr.com/65535/51808364707_c399307a51_o.png",
        "id_image": "inbox_547045"
      },
      {
        "link_thumb": "https://live.staticflickr.com/65535/51809674904_6d8ba177f4_n.jpg",
        "link_img": "https://live.staticflickr.com/65535/51809674904_595571f8f3_o.png",
        "id_image": "inbox_5512567"
      }
    ],
    "hash_code_list_img": "635043948"
  },
  {
    "link_it": "https://github.com/lmbstudiocontact/cb_img_5000_it_2/raw/main/fog_cb_img_5000_it.json",
    "id_item": "fog_cb_img_5000_it",
    "id_album": "570943552",
    "english": "fog",
    "list_mean": [
      "sương mù",
      "bao phủ hay bị bao phủ bằng sương mù"
    ],
    "cau_en": "",
    "cau_vn": "",
    "hash_code_list_mean": "-1026956382",
    "list_img": [
      {
        "link_thumb": "https://live.staticflickr.com/65535/51808362702_79743e6f89_n.jpg",
        "link_img": "https://live.staticflickr.com/65535/51808362702_8791166b01_o.png",
        "id_image": "fog_1207561"
      },
      {
        "link_thumb": "https://live.staticflickr.com/65535/51808362662_4044df878a_n.jpg",
        "link_img": "https://live.staticflickr.com/65535/51808362662_9dddeb7fd7_o.png",
        "id_image": "fog_1327598"
      },
      {
        "link_thumb": "https://live.staticflickr.com/65535/51809433443_9026066d17_n.jpg",
        "link_img": "https://live.staticflickr.com/65535/51809433443_7cb1efd022_o.png",
        "id_image": "fog_286588"
      },
      {
        "link_thumb": "https://live.staticflickr.com/65535/51809433328_d6a2e9f9a8_n.jpg",
        "link_img": "https://live.staticflickr.com/65535/51809433328_f67f212cc0_o.png",
        "id_image": "fog_6183091"
      }
    ],
    "hash_code_list_img": "1693339944"
  },
  {
    "link_it": "https://github.com/lmbstudiocontact/cb_img_5000_it_2/raw/main/landslide_cb_img_5000_it.json",
    "id_item": "landslide_cb_img_5000_it",
    "id_album": "570943552",
    "english": "landslide",
    "list_mean": [
      "sự lở đất"
    ],
    "cau_en": "",
    "cau_vn": "",
    "hash_code_list_mean": "-785652940",
    "list_img": [
      {
        "link_thumb": "https://live.staticflickr.com/65535/51808365927_71f425da51_n.jpg",
        "link_img": "https://live.staticflickr.com/65535/51808365927_db82fcd6c6_o.png",
        "id_image": "landslide_286591"
      },
      {
        "link_thumb": "https://live.staticflickr.com/65535/51808365847_8976a218e9_n.jpg",
        "link_img": "https://live.staticflickr.com/65535/51808365847_446a625291_o.png",
        "id_image": "landslide_3436090"
      },
      {
        "link_thumb": "https://live.staticflickr.com/65535/51809436198_9dfa5b36da_n.jpg",
        "link_img": "https://live.staticflickr.com/65535/51809436198_158e2301f0_o.png",
        "id_image": "landslide_491248"
      },
      {
        "link_thumb": "https://live.staticflickr.com/65535/51810057730_47412df33a_n.jpg",
        "link_img": "https://live.staticflickr.com/65535/51810057730_28c17dc5be_o.png",
        "id_image": "landslide_491250"
      }
    ],
    "hash_code_list_img": "-1874021833"
  },
  {
    "link_it": "https://github.com/lmbstudiocontact/cb_img_5000_it_2/raw/main/karate_cb_img_5000_it.json",
    "id_item": "karate_cb_img_5000_it",
    "id_album": "570943552",
    "english": "karate",
    "list_mean": [
      "môn võ Ka ra te"
    ],
    "cau_en": "",
    "cau_vn": "",
    "hash_code_list_mean": "-1479136449",
    "list_img": [
      {
        "link_thumb": "https://live.staticflickr.com/65535/51809329846_e2338958ae_n.jpg",
        "link_img": "https://live.staticflickr.com/65535/51809329846_8984e6a111_o.png",
        "id_image": "karate_2955022"
      },
      {
        "link_thumb": "https://live.staticflickr.com/65535/51808374422_1b6f6164c1_n.jpg",
        "link_img": "https://live.staticflickr.com/65535/51808374422_de93a13422_o.png",
        "id_image": "karate_6207817"
      },
      {
        "link_thumb": "https://live.staticflickr.com/65535/51808374507_a196132cc8_n.jpg",
        "link_img": "https://live.staticflickr.com/65535/51808374507_d33c83ac1b_o.png",
        "id_image": "karate_928665"
      }
    ],
    "hash_code_list_img": "676100189"
  },
  {
    "link_it": "https://github.com/lmbstudiocontact/cb_img_5000_it_3/raw/main/queen_cb_img_5000_it.json",
    "id_item": "queen_cb_img_5000_it",
    "id_album": "570943552",
    "english": "queen",
    "list_mean": [
      "nữ hoàng",
      "hoàng hậu",
      "nữ chúa",
      "quân đầm",
      "quân hậu",
      "ong chúa; kiến chúa",
      "kẻ đồng tính luyến ái"
    ],
    "cau_en": "",
    "cau_vn": "",
    "hash_code_list_mean": "-2020740577",
    "list_img": [
      {
        "link_thumb": "https://live.staticflickr.com/65535/51808389372_b2e15a5c56_n.jpg",
        "link_img": "https://live.staticflickr.com/65535/51808389372_a19f801ca1_o.png",
        "id_image": "queen_2349515"
      },
      {
        "link_thumb": "https://live.staticflickr.com/65535/51809459148_2c2f2117a4_n.jpg",
        "link_img": "https://live.staticflickr.com/65535/51809459148_e75d5038c1_o.png",
        "id_image": "queen_4133591"
      }
    ],
    "hash_code_list_img": "325876112"
  },
  {
    "link_it": "https://github.com/lmbstudiocontact/cb_img_5000_it_3/raw/main/principal_cb_img_5000_it.json",
    "id_item": "principal_cb_img_5000_it",
    "id_album": "570943552",
    "english": "principal",
    "list_mean": [
      "chính",
      "hiệu trưởng",
      "nhân vật chính",
      "tiền gốc"
    ],
    "cau_en": "",
    "cau_vn": "",
    "hash_code_list_mean": "-1937222580",
    "list_img": [
      {
        "link_thumb": "https://live.staticflickr.com/65535/51809440288_960baea935_n.jpg",
        "link_img": "https://live.staticflickr.com/65535/51809440288_faa268282b_o.png",
        "id_image": "principal_2141396"
      },
      {
        "link_thumb": "https://live.staticflickr.com/65535/51809440243_2b75862086_n.jpg",
        "link_img": "https://live.staticflickr.com/65535/51809440243_b9f1a0c877_o.png",
        "id_image": "principal_4711047"
      },
      {
        "link_thumb": "https://live.staticflickr.com/65535/51809440208_3ba27f939d_n.jpg",
        "link_img": "https://live.staticflickr.com/65535/51809440208_21163fed7c_o.png",
        "id_image": "principal_6032224"
      }
    ],
    "hash_code_list_img": "-1545516963"
  },
  {
    "link_it": "https://github.com/lmbstudiocontact/cb_img_5000_it_2/raw/main/hearth_cb_img_5000_it.json",
    "id_item": "hearth_cb_img_5000_it",
    "id_album": "570943552",
    "english": "hearth",
    "list_mean": [
      "lò sưởi"
    ],
    "cau_en": "",
    "cau_vn": "",
    "hash_code_list_mean": "-266924096",
    "list_img": [
      {
        "link_thumb": "https://live.staticflickr.com/65535/51808385312_ca5cd7cac2_n.jpg",
        "link_img": "https://live.staticflickr.com/65535/51808385312_06342d51b3_o.png",
        "id_image": "hearth_1839331"
      },
      {
        "link_thumb": "https://live.staticflickr.com/65535/51809455218_f56a03b411_n.jpg",
        "link_img": "https://live.staticflickr.com/65535/51809455218_4798bd4f21_o.png",
        "id_image": "hearth_2548525"
      },
      {
        "link_thumb": "https://live.staticflickr.com/65535/51810077675_b19009e949_n.jpg",
        "link_img": "https://live.staticflickr.com/65535/51810077675_d420fd437f_o.png",
        "id_image": "hearth_351895"
      }
    ],
    "hash_code_list_img": "72413638"
  },
  {
    "link_it": "https://github.com/lmbstudiocontact/cb_img_5000_it_2/raw/main/leaf_cb_img_5000_it.json",
    "id_item": "leaf_cb_img_5000_it",
    "id_album": "570943552",
    "english": "leaf",
    "list_mean": [
      "lá cây",
      "tờ (giấy)",
      "tấm ghép"
    ],
    "cau_en": "",
    "cau_vn": "",
    "hash_code_list_mean": "672707768",
    "list_img": [
      {
        "link_thumb": "https://live.staticflickr.com/65535/51808361922_74dc81c82a_n.jpg",
        "link_img": "https://live.staticflickr.com/65535/51808361922_852dcbb632_o.png",
        "id_image": "leaf_169819"
      },
      {
        "link_thumb": "https://live.staticflickr.com/65535/51809317596_37fc531d06_n.jpg",
        "link_img": "https://live.staticflickr.com/65535/51809317596_421a92d12d_o.png",
        "id_image": "leaf_263930"
      },
      {
        "link_thumb": "https://live.staticflickr.com/65535/51809432693_8e7066c15b_n.jpg",
        "link_img": "https://live.staticflickr.com/65535/51809432693_549551f064_o.png",
        "id_image": "leaf_692063"
      },
      {
        "link_thumb": "https://live.staticflickr.com/65535/51809317561_dbbf8a4d1d_n.jpg",
        "link_img": "https://live.staticflickr.com/65535/51809317561_4dfa43004d_o.png",
        "id_image": "leaf_921825"
      }
    ],
    "hash_code_list_img": "-815837996"
  },
  {
    "link_it": "https://github.com/lmbstudiocontact/cb_img_5000_it_2/raw/main/kitty_cb_img_5000_it.json",
    "id_item": "kitty_cb_img_5000_it",
    "id_album": "570943552",
    "english": "kitty",
    "list_mean": [
      "vốn được góp"
    ],
    "cau_en": "",
    "cau_vn": "",
    "hash_code_list_mean": "764286127",
    "list_img": [
      {
        "link_thumb": "https://live.staticflickr.com/65535/51810063085_68c058ba6e_n.jpg",
        "link_img": "https://live.staticflickr.com/65535/51810063085_3bb93e805d_o.png",
        "id_image": "kitty_763743"
      }
    ],
    "hash_code_list_img": "1105964589"
  },
  {
    "link_it": "https://github.com/lmbstudiocontact/cb_img_5000_it_2/raw/main/immune_cb_img_5000_it.json",
    "id_item": "immune_cb_img_5000_it",
    "id_album": "570943552",
    "english": "immune",
    "list_mean": [
      "miễn khỏi"
    ],
    "cau_en": "",
    "cau_vn": "",
    "hash_code_list_mean": "709479441",
    "list_img": [
      {
        "link_thumb": "https://live.staticflickr.com/65535/51809437318_6607383528_n.jpg",
        "link_img": "https://live.staticflickr.com/65535/51809437318_f426ae5279_o.png",
        "id_image": "immune_5730167"
      },
      {
        "link_thumb": "https://live.staticflickr.com/65535/51809322051_cbf6cf045e_n.jpg",
        "link_img": "https://live.staticflickr.com/65535/51809322051_bb8c42c649_o.png",
        "id_image": "immune_6181888"
      }
    ],
    "hash_code_list_img": "-908366372"
  },
  {
    "link_it": "https://github.com/lmbstudiocontact/cb_img_5000_it_2/raw/main/foil_cb_img_5000_it.json",
    "id_item": "foil_cb_img_5000_it",
    "id_album": "570943552",
    "english": "foil",
    "list_mean": [
      "làm thất bại (một âm mưu, một kế hoạch…)",
      "lá (kim loại)",
      "người hay vật tôn người hay vật khác lên (khi so sánh)",
      "kiếm bịt đầu"
    ],
    "cau_en": "",
    "cau_vn": "",
    "hash_code_list_mean": "1697257274",
    "list_img": [
      {
        "link_thumb": "https://live.staticflickr.com/65535/51810054610_39be0ddf13_n.jpg",
        "link_img": "https://live.staticflickr.com/65535/51810054610_422e46a92a_o.png",
        "id_image": "foil_239248"
      },
      {
        "link_thumb": "https://live.staticflickr.com/65535/51809317986_7e593be906_n.jpg",
        "link_img": "https://live.staticflickr.com/65535/51809317986_83dc04acc7_o.png",
        "id_image": "foil_4802431"
      }
    ],
    "hash_code_list_img": "2079095300"
  },
  {
    "link_it": "https://github.com/lmbstudiocontact/cb_img_5000_it_1/raw/main/die_cb_img_5000_it.json",
    "id_item": "die_cb_img_5000_it",
    "id_album": "570943552",
    "english": "die",
    "list_mean": [
      "chết; qua đời",
      "mờ đi; biến mất",
      "khao khát",
      "khuôn rập"
    ],
    "cau_en": "",
    "cau_vn": "",
    "hash_code_list_mean": "1642134919",
    "list_img": [
      {
        "link_thumb": "https://live.staticflickr.com/65535/51809322801_1a04de47d3_n.jpg",
        "link_img": "https://live.staticflickr.com/65535/51809322801_92f1a1c6d9_o.png",
        "id_image": "die_3387107"
      }
    ],
    "hash_code_list_img": "1269848685"
  },
  {
    "link_it": "https://github.com/lmbstudiocontact/cb_img_5000_it_4/raw/main/seaside_cb_img_5000_it.json",
    "id_item": "seaside_cb_img_5000_it",
    "id_album": "570943552",
    "english": "seaside",
    "list_mean": [
      "bờ biển"
    ],
    "cau_en": "",
    "cau_vn": "",
    "hash_code_list_mean": "-325512458",
    "list_img": [
      {
        "link_thumb": "https://live.staticflickr.com/65535/51810061695_9cd80b4f4c_n.jpg",
        "link_img": "https://live.staticflickr.com/65535/51810061695_3e4ffedcb6_o.png",
        "id_image": "seaside_3038974"
      }
    ],
    "hash_code_list_img": "496914747"
  },
  {
    "link_it": "https://github.com/lmbstudiocontact/cb_img_5000_it_3/raw/main/recount_cb_img_5000_it.json",
    "id_item": "recount_cb_img_5000_it",
    "id_album": "570943552",
    "english": "recount",
    "list_mean": [
      "thuật lại",
      "đếm lại",
      "sự đếm lại"
    ],
    "cau_en": "",
    "cau_vn": "",
    "hash_code_list_mean": "-2118870695",
    "list_img": [
      {
        "link_thumb": "https://live.staticflickr.com/65535/51808379052_5f18f64ec4_n.jpg",
        "link_img": "https://live.staticflickr.com/65535/51808379052_e435bfe946_o.png",
        "id_image": "recount_5979033"
      }
    ],
    "hash_code_list_img": "1674565410"
  },
  {
    "link_it": "https://github.com/lmbstudiocontact/cb_img_5000_it_0/raw/main/bodyguard_cb_img_5000_it.json",
    "id_item": "bodyguard_cb_img_5000_it",
    "id_album": "570943552",
    "english": "bodyguard",
    "list_mean": [
      "vệ sĩ"
    ],
    "cau_en": "",
    "cau_vn": "",
    "hash_code_list_mean": "343733412",
    "list_img": [
      {
        "link_thumb": "https://live.staticflickr.com/65535/51810063505_9461e227b5_n.jpg",
        "link_img": "https://live.staticflickr.com/65535/51810063505_f28dfec2fe_o.png",
        "id_image": "bodyguard_3558010"
      },
      {
        "link_thumb": "https://live.staticflickr.com/65535/51809326586_036a52e09c_n.jpg",
        "link_img": "https://live.staticflickr.com/65535/51809326586_c2221a9a8a_o.png",
        "id_image": "bodyguard_4413038"
      },
      {
        "link_thumb": "https://live.staticflickr.com/65535/51809326546_e51239b565_n.jpg",
        "link_img": "https://live.staticflickr.com/65535/51809326546_15fb97810b_o.png",
        "id_image": "bodyguard_4413818"
      },
      {
        "link_thumb": "https://live.staticflickr.com/65535/51809441473_184655cfe9_n.jpg",
        "link_img": "https://live.staticflickr.com/65535/51809441473_feb3bc32c3_o.png",
        "id_image": "bodyguard_4441669"
      }
    ],
    "hash_code_list_img": "1271286739"
  },
  {
    "link_it": "https://github.com/lmbstudiocontact/cb_img_5000_it_0/raw/main/biochemistry_cb_img_5000_it.json",
    "id_item": "biochemistry_cb_img_5000_it",
    "id_album": "570943552",
    "english": "biochemistry",
    "list_mean": [
      "khoa hoá sinh"
    ],
    "cau_en": "",
    "cau_vn": "",
    "hash_code_list_mean": "498287462",
    "list_img": [
      {
        "link_thumb": "https://live.staticflickr.com/65535/51808348852_b317a7085d_n.jpg",
        "link_img": "https://live.staticflickr.com/65535/51808348852_50d6168b4c_o.png",
        "id_image": "biochemistry_4061195"
      },
      {
        "link_thumb": "https://live.staticflickr.com/65535/51809304676_000fff57aa_n.jpg",
        "link_img": "https://live.staticflickr.com/65535/51809304676_5377b6ebaa_o.png",
        "id_image": "biochemistry_4507090"
      }
    ],
    "hash_code_list_img": "-1704799721"
  }
]