[
  {
    "link_it": "https://github.com/lmbstudiocontact/cb_img_5000_it_3/raw/main/reporter_cb_img_5000_it.json",
    "id_item": "reporter_cb_img_5000_it",
    "id_album": "570943400",
    "english": "reporter",
    "list_mean": [
      "phóng viên"
    ],
    "cau_en": "",
    "cau_vn": "",
    "hash_code_list_mean": "592905858",
    "list_img": [
      {
        "link_thumb": "https://live.staticflickr.com/65535/51809322971_babbe60840_n.jpg",
        "link_img": "https://live.staticflickr.com/65535/51809322971_01ba91c63f_o.png",
        "id_image": "reporter_1476626"
      },
      {
        "link_thumb": "https://live.staticflickr.com/65535/51808367882_1b604f5047_n.jpg",
        "link_img": "https://live.staticflickr.com/65535/51808367882_a13f9f3158_o.png",
        "id_image": "reporter_560267"
      }
    ],
    "hash_code_list_img": "-358072635"
  },
  {
    "link_it": "https://github.com/lmbstudiocontact/cb_img_5000_it_1/raw/main/firm_cb_img_5000_it.json",
    "id_item": "firm_cb_img_5000_it",
    "id_album": "570943400",
    "english": "firm",
    "list_mean": [
      "mạnh mẽ; chắc chắn",
      "xác định; không thay đổi",
      "hãng; công ty"
    ],
    "cau_en": "",
    "cau_vn": "",
    "hash_code_list_mean": "-188437691",
    "list_img": [
      {
        "link_thumb": "https://live.staticflickr.com/65535/51809680799_7645c1de7e_n.jpg",
        "link_img": "https://live.staticflickr.com/65535/51809680799_fd18b7b1c3_o.png",
        "id_image": "firm_1622690"
      }
    ],
    "hash_code_list_img": "1711756134"
  },
  {
    "link_it": "https://github.com/lmbstudiocontact/cb_img_5000_it_2/raw/main/graduation_cb_img_5000_it.json",
    "id_item": "graduation_cb_img_5000_it",
    "id_album": "570943400",
    "english": "graduation",
    "list_mean": [
      "sự tốt nghiệp",
      "chia từng độ"
    ],
    "cau_en": "",
    "cau_vn": "",
    "hash_code_list_mean": "63208360",
    "list_img": [
      {
        "link_thumb": "https://live.staticflickr.com/65535/51809441268_640009615a_n.jpg",
        "link_img": "https://live.staticflickr.com/65535/51809441268_d9685e9bc9_o.png",
        "id_image": "graduation_401558"
      },
      {
        "link_thumb": "https://live.staticflickr.com/65535/51809441158_594c0abf0a_n.jpg",
        "link_img": "https://live.staticflickr.com/65535/51809441158_8ac1209a37_o.png",
        "id_image": "graduation_4334764"
      },
      {
        "link_thumb": "https://live.staticflickr.com/65535/51808370937_8e17c0f35b_n.jpg",
        "link_img": "https://live.staticflickr.com/65535/51808370937_1247c4a3c9_o.png",
        "id_image": "graduation_4832351"
      },
      {
        "link_thumb": "https://live.staticflickr.com/65535/51810063150_ba00a2ca95_n.jpg",
        "link_img": "https://live.staticflickr.com/65535/51810063150_cf9ac87c7d_o.png",
        "id_image": "graduation_769654"
      },
      {
        "link_thumb": "https://live.staticflickr.com/65535/51808371007_30c54a29ea_n.jpg",
        "link_img": "https://live.staticflickr.com/65535/51808371007_a47b7945d6_o.png",
        "id_image": "graduation_859969"
      }
    ],
    "hash_code_list_img": "903996378"
  },
  {
    "link_it": "https://github.com/lmbstudiocontact/cb_img_5000_it_3/raw/main/number_cb_img_5000_it.json",
    "id_item": "number_cb_img_5000_it",
    "id_album": "570943400",
    "english": "number",
    "list_mean": [
      "chữ số",
      "số lượng",
      "số phát hành của tạp chí",
      "tiết mục",
      "ghi số",
      "gồm có",
      "đánh số"
    ],
    "cau_en": "",
    "cau_vn": "",
    "hash_code_list_mean": "-103950000",
    "list_img": [
      {
        "link_thumb": "https://live.staticflickr.com/65535/51809674574_7e1b68d975_n.jpg",
        "link_img": "https://live.staticflickr.com/65535/51809674574_c05c0c77b6_o.png",
        "id_image": "number_1770951"
      },
      {
        "link_thumb": "https://live.staticflickr.com/65535/51809319671_1921267177_n.jpg",
        "link_img": "https://live.staticflickr.com/65535/51809319671_ca96572a74_o.png",
        "id_image": "number_2248043"
      }
    ],
    "hash_code_list_img": "1339167694"
  },
  {
    "link_it": "https://github.com/lmbstudiocontact/cb_img_5000_it_2/raw/main/management_cb_img_5000_it.json",
    "id_item": "management_cb_img_5000_it",
    "id_album": "570943400",
    "english": "management",
    "list_mean": [
      "việc quản lý",
      "ban quản lý"
    ],
    "cau_en": "",
    "cau_vn": "",
    "hash_code_list_mean": "190198145",
    "list_img": [
      {
        "link_thumb": "https://live.staticflickr.com/65535/51810063745_613f70df20_n.jpg",
        "link_img": "https://live.staticflickr.com/65535/51810063745_0555c0f0ae_o.png",
        "id_image": "management_1262761"
      },
      {
        "link_thumb": "https://live.staticflickr.com/65535/51809441813_9b3eec4068_n.jpg",
        "link_img": "https://live.staticflickr.com/65535/51809441813_45ebcbbc01_o.png",
        "id_image": "management_1285494"
      },
      {
        "link_thumb": "https://live.staticflickr.com/65535/51810063645_ab7343b96b_n.jpg",
        "link_img": "https://live.staticflickr.com/65535/51810063645_d59e4665c3_o.png",
        "id_image": "management_2494813"
      },
      {
        "link_thumb": "https://live.staticflickr.com/65535/51809441703_db9b582e3e_n.jpg",
        "link_img": "https://live.staticflickr.com/65535/51809441703_8a51d31178_o.png",
        "id_image": "management_3380748"
      },
      {
        "link_thumb": "https://live.staticflickr.com/65535/51809681979_4e38e6c6a3_n.jpg",
        "link_img": "https://live.staticflickr.com/65535/51809681979_89c3f4c970_o.png",
        "id_image": "management_943764"
      }
    ],
    "hash_code_list_img": "-147042962"
  },
  {
    "link_it": "https://github.com/lmbstudiocontact/cb_img_5000_it_4/raw/main/suffrage_cb_img_5000_it.json",
    "id_item": "suffrage_cb_img_5000_it",
    "id_album": "570943400",
    "english": "suffrage",
    "list_mean": [
      "quyền đi bầu",
      "sự bỏ phiếu"
    ],
    "cau_en": "",
    "cau_vn": "",
    "hash_code_list_mean": "-2057782607",
    "list_img": [
      {
        "link_thumb": "https://live.staticflickr.com/65535/51809338961_5a1c320b4f_n.jpg",
        "link_img": "https://live.staticflickr.com/65535/51809338961_66efa2dc8a_o.png",
        "id_image": "suffrage_1425432"
      },
      {
        "link_thumb": "https://live.staticflickr.com/65535/51809453908_d37c85c288_n.jpg",
        "link_img": "https://live.staticflickr.com/65535/51809453908_882597218f_o.png",
        "id_image": "suffrage_5234470"
      }
    ],
    "hash_code_list_img": "847520801"
  },
  {
    "link_it": "https://github.com/lmbstudiocontact/cb_img_5000_it_2/raw/main/horseman_cb_img_5000_it.json",
    "id_item": "horseman_cb_img_5000_it",
    "id_album": "570943400",
    "english": "horseman",
    "list_mean": [
      "kỵ sĩ"
    ],
    "cau_en": "",
    "cau_vn": "",
    "hash_code_list_mean": "334945067",
    "list_img": [
      {
        "link_thumb": "https://live.staticflickr.com/65535/51809686404_cd3fa477af_n.jpg",
        "link_img": "https://live.staticflickr.com/65535/51809686404_1935f0b7f7_o.png",
        "id_image": "horseman_1354463"
      },
      {
        "link_thumb": "https://live.staticflickr.com/65535/51808376042_230d2fe985_n.jpg",
        "link_img": "https://live.staticflickr.com/65535/51808376042_a2e6b91588_o.png",
        "id_image": "horseman_1499919"
      }
    ],
    "hash_code_list_img": "1016516379"
  },
  {
    "link_it": "https://github.com/lmbstudiocontact/cb_img_5000_it_3/raw/main/nap_cb_img_5000_it.json",
    "id_item": "nap_cb_img_5000_it",
    "id_album": "570943400",
    "english": "nap",
    "list_mean": [
      "giấc ngủ ngắn"
    ],
    "cau_en": "",
    "cau_vn": "",
    "hash_code_list_mean": "-1932375767",
    "list_img": [
      {
        "link_thumb": "https://live.staticflickr.com/65535/51809443683_39e4c80ea9_n.jpg",
        "link_img": "https://live.staticflickr.com/65535/51809443683_1ceb6ddcd5_o.png",
        "id_image": "nap_1702344"
      },
      {
        "link_thumb": "https://live.staticflickr.com/65535/51809328666_c1dc2171df_n.jpg",
        "link_img": "https://live.staticflickr.com/65535/51809328666_7a829b9b17_o.png",
        "id_image": "nap_2964763"
      },
      {
        "link_thumb": "https://live.staticflickr.com/65535/51809683684_fce40481a3_n.jpg",
        "link_img": "https://live.staticflickr.com/65535/51809683684_3c8a30ab4d_o.png",
        "id_image": "nap_3310318"
      },
      {
        "link_thumb": "https://live.staticflickr.com/65535/51808373327_4566cd57fb_n.jpg",
        "link_img": "https://live.staticflickr.com/65535/51808373327_d45643ebe1_o.png",
        "id_image": "nap_3310321"
      },
      {
        "link_thumb": "https://live.staticflickr.com/65535/51808373302_be5dcc008b_n.jpg",
        "link_img": "https://live.staticflickr.com/65535/51808373302_a30bd1ddac_o.png",
        "id_image": "nap_5775901"
      }
    ],
    "hash_code_list_img": "1611215887"
  },
  {
    "link_it": "https://github.com/lmbstudiocontact/cb_img_5000_it_1/raw/main/complain_cb_img_5000_it.json",
    "id_item": "complain_cb_img_5000_it",
    "id_album": "570943400",
    "english": "complain",
    "list_mean": [
      "than phiền",
      "kể lại một sự đau đớn"
    ],
    "cau_en": "",
    "cau_vn": "",
    "hash_code_list_mean": "-836040779",
    "list_img": [
      {
        "link_thumb": "https://live.staticflickr.com/65535/51810052800_b0ca40b253_n.jpg",
        "link_img": "https://live.staticflickr.com/65535/51810052800_6508868891_o.png",
        "id_image": "complain_2016314"
      },
      {
        "link_thumb": "https://live.staticflickr.com/65535/51809316381_d9ec73c210_n.jpg",
        "link_img": "https://live.staticflickr.com/65535/51809316381_dc92d43022_o.png",
        "id_image": "complain_5692381"
      }
    ],
    "hash_code_list_img": "445979613"
  },
  {
    "link_it": "https://github.com/lmbstudiocontact/cb_img_5000_it_1/raw/main/executive_cb_img_5000_it.json",
    "id_item": "executive_cb_img_5000_it",
    "id_album": "570943400",
    "english": "executive",
    "list_mean": [
      "điều hành",
      "hành pháp",
      "ngành hành pháp",
      "uỷ viên ban quản trị"
    ],
    "cau_en": "",
    "cau_vn": "",
    "hash_code_list_mean": "1475411666",
    "list_img": [
      {
        "link_thumb": "https://live.staticflickr.com/65535/51809426698_c1d5b678c0_n.jpg",
        "link_img": "https://live.staticflickr.com/65535/51809426698_ec482ae7c5_o.png",
        "id_image": "executive_2111179"
      },
      {
        "link_thumb": "https://live.staticflickr.com/65535/51808355887_c6659129e0_n.jpg",
        "link_img": "https://live.staticflickr.com/65535/51808355887_0ac6743479_o.png",
        "id_image": "executive_2910466"
      },
      {
        "link_thumb": "https://live.staticflickr.com/65535/51809426608_d9bbcdca10_n.jpg",
        "link_img": "https://live.staticflickr.com/65535/51809426608_a870334463_o.png",
        "id_image": "executive_3603777"
      },
      {
        "link_thumb": "https://live.staticflickr.com/65535/51808355847_6c01cc7724_n.jpg",
        "link_img": "https://live.staticflickr.com/65535/51808355847_a995127a81_o.png",
        "id_image": "executive_5138170"
      },
      {
        "link_thumb": "https://live.staticflickr.com/65535/51809311696_bb4f7031fc_n.jpg",
        "link_img": "https://live.staticflickr.com/65535/51809311696_ce687b9904_o.png",
        "id_image": "executive_6078592"
      }
    ],
    "hash_code_list_img": "1028945999"
  },
  {
    "link_it": "https://github.com/lmbstudiocontact/cb_img_5000_it_3/raw/main/ribbon_cb_img_5000_it.json",
    "id_item": "ribbon_cb_img_5000_it",
    "id_album": "570943400",
    "english": "ribbon",
    "list_mean": [
      "dải ruy-băng"
    ],
    "cau_en": "",
    "cau_vn": "",
    "hash_code_list_mean": "-1757001434",
    "list_img": [
      {
        "link_thumb": "https://live.staticflickr.com/65535/51809702304_2b027b46af_n.jpg",
        "link_img": "https://live.staticflickr.com/65535/51809702304_2841640356_o.png",
        "id_image": "ribbon_1357111"
      },
      {
        "link_thumb": "https://live.staticflickr.com/65535/51809347571_810a6746f3_n.jpg",
        "link_img": "https://live.staticflickr.com/65535/51809347571_cd0f934fbc_o.png",
        "id_image": "ribbon_532028"
      }
    ],
    "hash_code_list_img": "-70308255"
  },
  {
    "link_it": "https://github.com/lmbstudiocontact/cb_img_5000_it_3/raw/main/remember_cb_img_5000_it.json",
    "id_item": "remember_cb_img_5000_it",
    "id_album": "570943400",
    "english": "remember",
    "list_mean": [
      "nhớ",
      "nhớ đến ai",
      "chuyển lời chúc đến ai"
    ],
    "cau_en": "",
    "cau_vn": "",
    "hash_code_list_mean": "2022246207",
    "list_img": [
      {
        "link_thumb": "https://live.staticflickr.com/65535/51809325956_83ffa68625_n.jpg",
        "link_img": "https://live.staticflickr.com/65535/51809325956_55933543a3_o.png",
        "id_image": "remember_5822099"
      },
      {
        "link_thumb": "https://live.staticflickr.com/65535/51809681029_c4b53462ec_n.jpg",
        "link_img": "https://live.staticflickr.com/65535/51809681029_4e6bbc6398_o.png",
        "id_image": "remember_5860861"
      }
    ],
    "hash_code_list_img": "-2121991988"
  },
  {
    "link_it": "https://github.com/lmbstudiocontact/cb_img_5000_it_0/raw/main/blindfold_cb_img_5000_it.json",
    "id_item": "blindfold_cb_img_5000_it",
    "id_album": "570943400",
    "english": "blindfold",
    "list_mean": [
      "dải băng bịt mắt",
      "bịt mắt",
      "bị bịt mắt"
    ],
    "cau_en": "",
    "cau_vn": "",
    "hash_code_list_mean": "2118796149",
    "list_img": [
      {
        "link_thumb": "https://live.staticflickr.com/65535/51808346827_cbceaee436_n.jpg",
        "link_img": "https://live.staticflickr.com/65535/51808346827_4c0f626a5c_o.png",
        "id_image": "blindfold_1818617"
      },
      {
        "link_thumb": "https://live.staticflickr.com/65535/51808346812_496834f691_n.jpg",
        "link_img": "https://live.staticflickr.com/65535/51808346812_6862154399_o.png",
        "id_image": "blindfold_4329457"
      },
      {
        "link_thumb": "https://live.staticflickr.com/65535/51810039185_06780d28b0_n.jpg",
        "link_img": "https://live.staticflickr.com/65535/51810039185_0db8f16506_o.png",
        "id_image": "blindfold_5236548"
      },
      {
        "link_thumb": "https://live.staticflickr.com/65535/51809417658_9d8a75a8c9_n.jpg",
        "link_img": "https://live.staticflickr.com/65535/51809417658_a810f46d15_o.png",
        "id_image": "blindfold_6333063"
      }
    ],
    "hash_code_list_img": "384882895"
  },
  {
    "link_it": "https://github.com/lmbstudiocontact/cb_img_5000_it_4/raw/main/storage_cb_img_5000_it.json",
    "id_item": "storage_cb_img_5000_it",
    "id_album": "570943400",
    "english": "storage",
    "list_mean": [
      "sự xếp vào kho"
    ],
    "cau_en": "",
    "cau_vn": "",
    "hash_code_list_mean": "-1160597155",
    "list_img": [
      {
        "link_thumb": "https://live.staticflickr.com/65535/51809345126_6856a1ddac_n.jpg",
        "link_img": "https://live.staticflickr.com/65535/51809345126_1229d61593_o.png",
        "id_image": "storage_3944799"
      },
      {
        "link_thumb": "https://live.staticflickr.com/65535/51809459923_ac4df13b83_n.jpg",
        "link_img": "https://live.staticflickr.com/65535/51809459923_5143425dd2_o.png",
        "id_image": "storage_4899533"
      },
      {
        "link_thumb": "https://live.staticflickr.com/65535/51808390017_24f8c59171_n.jpg",
        "link_img": "https://live.staticflickr.com/65535/51808390017_1b8e5606f8_o.png",
        "id_image": "storage_4944329"
      }
    ],
    "hash_code_list_img": "-1116841435"
  },
  {
    "link_it": "https://github.com/lmbstudiocontact/cb_img_5000_it_2/raw/main/lady_cb_img_5000_it.json",
    "id_item": "lady_cb_img_5000_it",
    "id_album": "570943400",
    "english": "lady",
    "list_mean": [
      "quý bà",
      "cô nương, tiểu thư"
    ],
    "cau_en": "",
    "cau_vn": "",
    "hash_code_list_mean": "-1838326276",
    "list_img": [
      {
        "link_thumb": "https://live.staticflickr.com/65535/51809438118_8c6096833e_n.jpg",
        "link_img": "https://live.staticflickr.com/65535/51809438118_e9e014cc6c_o.png",
        "id_image": "lady_332062"
      },
      {
        "link_thumb": "https://live.staticflickr.com/65535/51808367867_3848beb8cc_n.jpg",
        "link_img": "https://live.staticflickr.com/65535/51808367867_538de390e6_o.png",
        "id_image": "lady_819561"
      }
    ],
    "hash_code_list_img": "-2091271352"
  },
  {
    "link_it": "https://github.com/lmbstudiocontact/cb_img_5000_it_1/raw/main/float_cb_img_5000_it.json",
    "id_item": "float_cb_img_5000_it",
    "id_album": "570943400",
    "english": "float",
    "list_mean": [
      "lơ lửng; lềnh bềnh; nổi",
      "cái phao",
      "bè; mảng trôi"
    ],
    "cau_en": "",
    "cau_vn": "",
    "hash_code_list_mean": "84452762",
    "list_img": [
      {
        "link_thumb": "https://live.staticflickr.com/65535/51809436333_a4aff994f1_n.jpg",
        "link_img": "https://live.staticflickr.com/65535/51809436333_e66552a51d_o.png",
        "id_image": "float_390806"
      },
      {
        "link_thumb": "https://live.staticflickr.com/65535/51810057810_7cce6eb71c_n.jpg",
        "link_img": "https://live.staticflickr.com/65535/51810057810_be23890073_o.png",
        "id_image": "float_4861733"
      },
      {
        "link_thumb": "https://live.staticflickr.com/65535/51808365952_e05fcdfda5_n.jpg",
        "link_img": "https://live.staticflickr.com/65535/51808365952_5fef925ddc_o.png",
        "id_image": "float_499416"
      }
    ],
    "hash_code_list_img": "-130542566"
  },
  {
    "link_it": "https://github.com/lmbstudiocontact/cb_img_5000_it_1/raw/main/flavour_cb_img_5000_it.json",
    "id_item": "flavour_cb_img_5000_it",
    "id_album": "570943400",
    "english": "flavour",
    "list_mean": [
      "vị ngon; mùi thơm; mùi vị",
      "hương vị",
      "cho gia vị; thêm gia vị"
    ],
    "cau_en": "",
    "cau_vn": "",
    "hash_code_list_mean": "-1189585070",
    "list_img": [
      {
        "link_thumb": "https://live.staticflickr.com/65535/51809677124_4c8d423cf2_n.jpg",
        "link_img": "https://live.staticflickr.com/65535/51809677124_227dab3acb_o.png",
        "id_image": "flavour_527773"
      }
    ],
    "hash_code_list_img": "1340508116"
  },
  {
    "link_it": "https://github.com/lmbstudiocontact/cb_img_5000_it_1/raw/main/evidence_cb_img_5000_it.json",
    "id_item": "evidence_cb_img_5000_it",
    "id_album": "570943400",
    "english": "evidence",
    "list_mean": [
      "bằng chứng",
      "dấu hiệu"
    ],
    "cau_en": "",
    "cau_vn": "",
    "hash_code_list_mean": "-855684041",
    "list_img": [
      {
        "link_thumb": "https://live.staticflickr.com/65535/51809313386_95c929dc5e_n.jpg",
        "link_img": "https://live.staticflickr.com/65535/51809313386_dd74e01d4a_o.png",
        "id_image": "evidence_2034524"
      },
      {
        "link_thumb": "https://live.staticflickr.com/65535/51810049890_d2f9fc3b9b_n.jpg",
        "link_img": "https://live.staticflickr.com/65535/51810049890_0d9721ddb4_o.png",
        "id_image": "evidence_2322927"
      },
      {
        "link_thumb": "https://live.staticflickr.com/65535/51808357347_fb173ffe23_n.jpg",
        "link_img": "https://live.staticflickr.com/65535/51808357347_e5b43f84b7_o.png",
        "id_image": "evidence_2399410"
      },
      {
        "link_thumb": "https://live.staticflickr.com/65535/51809668209_18029b347b_n.jpg",
        "link_img": "https://live.staticflickr.com/65535/51809668209_c837a621ec_o.png",
        "id_image": "evidence_533968"
      }
    ],
    "hash_code_list_img": "-1181154047"
  },
  {
    "link_it": "https://github.com/lmbstudiocontact/cb_img_5000_it_2/raw/main/increment_cb_img_5000_it.json",
    "id_item": "increment_cb_img_5000_it",
    "id_album": "570943400",
    "english": "increment",
    "list_mean": [
      "sự tăng lương"
    ],
    "cau_en": "",
    "cau_vn": "",
    "hash_code_list_mean": "-1404154529",
    "list_img": [
      {
        "link_thumb": "https://live.staticflickr.com/65535/51808363117_d1fdec776b_n.jpg",
        "link_img": "https://live.staticflickr.com/65535/51808363117_91a5d0cf72_o.png",
        "id_image": "increment_1933944"
      },
      {
        "link_thumb": "https://live.staticflickr.com/65535/51809318531_9687692ce8_n.jpg",
        "link_img": "https://live.staticflickr.com/65535/51809318531_87f2b0f1d5_o.png",
        "id_image": "increment_5672051"
      }
    ],
    "hash_code_list_img": "-395569578"
  },
  {
    "link_it": "https://github.com/lmbstudiocontact/cb_img_5000_it_2/raw/main/mesh_cb_img_5000_it.json",
    "id_item": "mesh_cb_img_5000_it",
    "id_album": "570943400",
    "english": "mesh",
    "list_mean": [
      "mắt lưới",
      "mạng lưới",
      "dồn vào lưới"
    ],
    "cau_en": "",
    "cau_vn": "",
    "hash_code_list_mean": "1376628456",
    "list_img": [
      {
        "link_thumb": "https://live.staticflickr.com/65535/51808391087_8017b124f0_n.jpg",
        "link_img": "https://live.staticflickr.com/65535/51808391087_f98cf6b9ee_o.png",
        "id_image": "mesh_5672433"
      },
      {
        "link_thumb": "https://live.staticflickr.com/65535/51810083530_64ebc38d63_n.jpg",
        "link_img": "https://live.staticflickr.com/65535/51810083530_530f384048_o.png",
        "id_image": "mesh_5672436"
      }
    ],
    "hash_code_list_img": "681383381"
  },
  {
    "link_it": "https://github.com/lmbstudiocontact/cb_img_5000_it_0/raw/main/bend_cb_img_5000_it.json",
    "id_item": "bend_cb_img_5000_it",
    "id_album": "570943400",
    "english": "bend",
    "list_mean": [
      "cúi xuống; làm cong",
      "bắt phải theo",
      "chỗ uốn"
    ],
    "cau_en": "",
    "cau_vn": "",
    "hash_code_list_mean": "355100396",
    "list_img": [
      {
        "link_thumb": "https://live.staticflickr.com/65535/51808351962_c4a3d31623_n.jpg",
        "link_img": "https://live.staticflickr.com/65535/51808351962_44f5eb940c_o.png",
        "id_image": "bending_1055057"
      },
      {
        "link_thumb": "https://live.staticflickr.com/65535/51809307806_867883d40e_n.jpg",
        "link_img": "https://live.staticflickr.com/65535/51809307806_bb4ab4be4e_o.png",
        "id_image": "bending_1055085"
      },
      {
        "link_thumb": "https://live.staticflickr.com/65535/51808351912_cba33dcb4b_n.jpg",
        "link_img": "https://live.staticflickr.com/65535/51808351912_e0bb7dd578_o.png",
        "id_image": "bending_2450532"
      }
    ],
    "hash_code_list_img": "1704039601"
  },
  {
    "link_it": "https://github.com/lmbstudiocontact/cb_img_5000_it_1/raw/main/construction_cb_img_5000_it.json",
    "id_item": "construction_cb_img_5000_it",
    "id_album": "570943400",
    "english": "construction",
    "list_mean": [
      "sự xây dựng",
      "công trình xây dựng"
    ],
    "cau_en": "",
    "cau_vn": "",
    "hash_code_list_mean": "-1659598067",
    "list_img": [
      {
        "link_thumb": "https://live.staticflickr.com/65535/51810046120_54766d8537_n.jpg",
        "link_img": "https://live.staticflickr.com/65535/51810046120_2720db9874_o.png",
        "id_image": "construction_1207116"
      },
      {
        "link_thumb": "https://live.staticflickr.com/65535/51809309086_930b97a94d_n.jpg",
        "link_img": "https://live.staticflickr.com/65535/51809309086_68e6795855_o.png",
        "id_image": "construction_1207144"
      },
      {
        "link_thumb": "https://live.staticflickr.com/65535/51808353287_0c698ff7b5_n.jpg",
        "link_img": "https://live.staticflickr.com/65535/51808353287_d642fd8eb9_o.png",
        "id_image": "construction_2827372"
      },
      {
        "link_thumb": "https://live.staticflickr.com/65535/51810046080_59d10cbf78_n.jpg",
        "link_img": "https://live.staticflickr.com/65535/51810046080_be857ebb04_o.png",
        "id_image": "construction_3752626"
      },
      {
        "link_thumb": "https://live.staticflickr.com/65535/51809309061_638729c44c_n.jpg",
        "link_img": "https://live.staticflickr.com/65535/51809309061_3457cd3b6c_o.png",
        "id_image": "construction_6258513"
      }
    ],
    "hash_code_list_img": "-1035272355"
  },
  {
    "link_it": "https://github.com/lmbstudiocontact/cb_img_5000_it_2/raw/main/mascot_cb_img_5000_it.json",
    "id_item": "mascot_cb_img_5000_it",
    "id_album": "570943400",
    "english": "mascot",
    "list_mean": [
      "linh vật"
    ],
    "cau_en": "",
    "cau_vn": "",
    "hash_code_list_mean": "1190124243",
    "list_img": [
      {
        "link_thumb": "https://live.staticflickr.com/65535/51809436988_dd451d2aeb_n.jpg",
        "link_img": "https://live.staticflickr.com/65535/51809436988_75188caeda_o.png",
        "id_image": "mascot_1754012"
      },
      {
        "link_thumb": "https://live.staticflickr.com/65535/51809321786_3a1b2816df_n.jpg",
        "link_img": "https://live.staticflickr.com/65535/51809321786_0b3318efb8_o.png",
        "id_image": "mascot_4213298"
      },
      {
        "link_thumb": "https://live.staticflickr.com/65535/51809676819_c4618f89f4_n.jpg",
        "link_img": "https://live.staticflickr.com/65535/51809676819_c249a205cf_o.png",
        "id_image": "mascot_4443736"
      },
      {
        "link_thumb": "https://live.staticflickr.com/65535/51809676804_dd7a3a67bb_n.jpg",
        "link_img": "https://live.staticflickr.com/65535/51809676804_e5666ec970_o.png",
        "id_image": "mascot_5978320"
      }
    ],
    "hash_code_list_img": "-1156467490"
  },
  {
    "link_it": "https://github.com/lmbstudiocontact/cb_img_5000_it_1/raw/main/courgette_cb_img_5000_it.json",
    "id_item": "courgette_cb_img_5000_it",
    "id_album": "570943400",
    "english": "courgette",
    "list_mean": [
      "bí xanh"
    ],
    "cau_en": "",
    "cau_vn": "",
    "hash_code_list_mean": "-695586633",
    "list_img": [
      {
        "link_thumb": "https://live.staticflickr.com/65535/51809681634_4781c3ae95_n.jpg",
        "link_img": "https://live.staticflickr.com/65535/51809681634_ce47a57c67_o.png",
        "id_image": "courgette_433666"
      },
      {
        "link_thumb": "https://live.staticflickr.com/65535/51809326551_7229efdbe9_n.jpg",
        "link_img": "https://live.staticflickr.com/65535/51809326551_1cf99f9e0a_o.png",
        "id_image": "courgette_877715"
      },
      {
        "link_thumb": "https://live.staticflickr.com/65535/51809326511_7a918628e5_n.jpg",
        "link_img": "https://live.staticflickr.com/65535/51809326511_d8a4462c0b_o.png",
        "id_image": "courgette_895192"
      }
    ],
    "hash_code_list_img": "-1804123223"
  },
  {
    "link_it": "https://github.com/lmbstudiocontact/cb_img_5000_it_0/raw/main/challenge_cb_img_5000_it.json",
    "id_item": "challenge_cb_img_5000_it",
    "id_album": "570943400",
    "english": "challenge",
    "list_mean": [
      "thách thức",
      "thẩm tra",
      "lời mời tham gia cuộc thi",
      "sự thẩm tra"
    ],
    "cau_en": "",
    "cau_vn": "",
    "hash_code_list_mean": "-707922982",
    "list_img": [
      {
        "link_thumb": "https://live.staticflickr.com/65535/51809429798_4824fe41b4_n.jpg",
        "link_img": "https://live.staticflickr.com/65535/51809429798_fa341c1988_o.png",
        "id_image": "challenges_1934019"
      },
      {
        "link_thumb": "https://live.staticflickr.com/65535/51808359032_99cbca0f6d_n.jpg",
        "link_img": "https://live.staticflickr.com/65535/51808359032_8cb26a97f8_o.png",
        "id_image": "challenges_3965814"
      },
      {
        "link_thumb": "https://live.staticflickr.com/65535/51809669654_2ff0b5dfba_n.jpg",
        "link_img": "https://live.staticflickr.com/65535/51809669654_197f14d0e7_o.png",
        "id_image": "challenge_2586919"
      },
      {
        "link_thumb": "https://live.staticflickr.com/65535/51809669639_d13d4501a2_n.jpg",
        "link_img": "https://live.staticflickr.com/65535/51809669639_0449077988_o.png",
        "id_image": "challenge_3310330"
      },
      {
        "link_thumb": "https://live.staticflickr.com/65535/51809669609_daa2238d37_n.jpg",
        "link_img": "https://live.staticflickr.com/65535/51809669609_7f6fed7ffb_o.png",
        "id_image": "challenge_3475873"
      }
    ],
    "hash_code_list_img": "-1623252828"
  },
  {
    "link_it": "https://github.com/lmbstudiocontact/cb_img_5000_it_4/raw/main/specimen_cb_img_5000_it.json",
    "id_item": "specimen_cb_img_5000_it",
    "id_album": "570943400",
    "english": "specimen",
    "list_mean": [
      "mẫu, mẫu vật"
    ],
    "cau_en": "",
    "cau_vn": "",
    "hash_code_list_mean": "-2020729656",
    "list_img": [
      {
        "link_thumb": "https://live.staticflickr.com/65535/51809679684_46751dd13c_n.jpg",
        "link_img": "https://live.staticflickr.com/65535/51809679684_1df313286d_o.png",
        "id_image": "specimen_3335633"
      },
      {
        "link_thumb": "https://live.staticflickr.com/65535/51809439533_bd6984f954_n.jpg",
        "link_img": "https://live.staticflickr.com/65535/51809439533_08dc880319_o.png",
        "id_image": "specimen_4118508"
      }
    ],
    "hash_code_list_img": "1878440582"
  },
  {
    "link_it": "https://github.com/lmbstudiocontact/cb_img_5000_it_1/raw/main/container_cb_img_5000_it.json",
    "id_item": "container_cb_img_5000_it",
    "id_album": "570943400",
    "english": "container",
    "list_mean": [
      "vật đựng (chai, lọ)",
      "công ten nơ"
    ],
    "cau_en": "",
    "cau_vn": "",
    "hash_code_list_mean": "1550511946",
    "list_img": [
      {
        "link_thumb": "https://live.staticflickr.com/65535/51809307826_4f9efdcfb8_n.jpg",
        "link_img": "https://live.staticflickr.com/65535/51809307826_691b9a1f12_o.png",
        "id_image": "container_1580227"
      },
      {
        "link_thumb": "https://live.staticflickr.com/65535/51808351942_0267cb6785_n.jpg",
        "link_img": "https://live.staticflickr.com/65535/51808351942_7abf3f42e9_o.png",
        "id_image": "container_1738098"
      },
      {
        "link_thumb": "https://live.staticflickr.com/65535/51808351897_efe2c3147f_n.jpg",
        "link_img": "https://live.staticflickr.com/65535/51808351897_37ec6448c3_o.png",
        "id_image": "container_1740635"
      },
      {
        "link_thumb": "https://live.staticflickr.com/65535/51809422913_97bdf20d91_n.jpg",
        "link_img": "https://live.staticflickr.com/65535/51809422913_c5fa8e744f_o.png",
        "id_image": "container_2928758"
      },
      {
        "link_thumb": "https://live.staticflickr.com/65535/51808351992_6172fff15e_n.jpg",
        "link_img": "https://live.staticflickr.com/65535/51808351992_685e8b3686_o.png",
        "id_image": "container_883694"
      }
    ],
    "hash_code_list_img": "-947387260"
  },
  {
    "link_it": "https://github.com/lmbstudiocontact/cb_img_5000_it_2/raw/main/lightbulb_cb_img_5000_it.json",
    "id_item": "lightbulb_cb_img_5000_it",
    "id_album": "570943400",
    "english": "lightbulb",
    "list_mean": [
      "bóng đèn"
    ],
    "cau_en": "",
    "cau_vn": "",
    "hash_code_list_mean": "-1137664352",
    "list_img": [
      {
        "link_thumb": "https://live.staticflickr.com/65535/51809457288_897ac0d9b5_n.jpg",
        "link_img": "https://live.staticflickr.com/65535/51809457288_c4b5e75aa8_o.png",
        "id_image": "lightbulb_1262709"
      },
      {
        "link_thumb": "https://live.staticflickr.com/65535/51810079935_6622288ebd_n.jpg",
        "link_img": "https://live.staticflickr.com/65535/51810079935_10c26c32eb_o.png",
        "id_image": "lightbulb_1262997"
      },
      {
        "link_thumb": "https://live.staticflickr.com/65535/51810080030_79edd997a2_n.jpg",
        "link_img": "https://live.staticflickr.com/65535/51810080030_d5114fa3e9_o.png",
        "id_image": "lightbulb_812875"
      }
    ],
    "hash_code_list_img": "-780169771"
  },
  {
    "link_it": "https://github.com/lmbstudiocontact/cb_img_5000_it_4/raw/main/sword_cb_img_5000_it.json",
    "id_item": "sword_cb_img_5000_it",
    "id_album": "570943400",
    "english": "sword",
    "list_mean": [
      "gươm, kiếm, đao"
    ],
    "cau_en": "",
    "cau_vn": "",
    "hash_code_list_mean": "-79275435",
    "list_img": [
      {
        "link_thumb": "https://live.staticflickr.com/65535/51809686539_7b91bdb4f8_n.jpg",
        "link_img": "https://live.staticflickr.com/65535/51809686539_3297b1ecba_o.png",
        "id_image": "sword_942409"
      }
    ],
    "hash_code_list_img": "1817497851"
  },
  {
    "link_it": "https://github.com/lmbstudiocontact/cb_img_5000_it_1/raw/main/diplomat_cb_img_5000_it.json",
    "id_item": "diplomat_cb_img_5000_it",
    "id_album": "570943400",
    "english": "diplomat",
    "list_mean": [
      "nhà ngoại giao"
    ],
    "cau_en": "",
    "cau_vn": "",
    "hash_code_list_mean": "-383443125",
    "list_img": [
      {
        "link_thumb": "https://live.staticflickr.com/65535/51809320356_d982f4551d_n.jpg",
        "link_img": "https://live.staticflickr.com/65535/51809320356_4032625a97_o.png",
        "id_image": "diplomat_4849734"
      }
    ],
    "hash_code_list_img": "1532954330"
  },
  {
    "link_it": "https://github.com/lmbstudiocontact/cb_img_5000_it_0/raw/main/assortment_cb_img_5000_it.json",
    "id_item": "assortment_cb_img_5000_it",
    "id_album": "570943400",
    "english": "assortment",
    "list_mean": [
      "đủ loại"
    ],
    "cau_en": "",
    "cau_vn": "",
    "hash_code_list_mean": "655403188",
    "list_img": [
      {
        "link_thumb": "https://live.staticflickr.com/65535/51810039450_89ca079930_n.jpg",
        "link_img": "https://live.staticflickr.com/65535/51810039450_f093411aa2_o.png",
        "id_image": "assortment_4827326"
      },
      {
        "link_thumb": "https://live.staticflickr.com/65535/51810039425_a1357abf06_n.jpg",
        "link_img": "https://live.staticflickr.com/65535/51810039425_541c7e4815_o.png",
        "id_image": "assortment_4994989"
      },
      {
        "link_thumb": "https://live.staticflickr.com/65535/51809302811_9c0fac854f_n.jpg",
        "link_img": "https://live.staticflickr.com/65535/51809302811_f287ea9986_o.png",
        "id_image": "assort_2104162"
      }
    ],
    "hash_code_list_img": "-2019414201"
  },
  {
    "link_it": "https://github.com/lmbstudiocontact/cb_img_5000_it_1/raw/main/copy_cb_img_5000_it.json",
    "id_item": "copy_cb_img_5000_it",
    "id_album": "570943400",
    "english": "copy",
    "list_mean": [
      "bản sao",
      "một bản của cuốn sách, tờ báo",
      "bản thảo",
      "sao chép"
    ],
    "cau_en": "",
    "cau_vn": "",
    "hash_code_list_mean": "-399465394",
    "list_img": [
      {
        "link_thumb": "https://live.staticflickr.com/65535/51809333261_344992194c_n.jpg",
        "link_img": "https://live.staticflickr.com/65535/51809333261_2f167fd420_o.png",
        "id_image": "copy_1265884"
      },
      {
        "link_thumb": "https://live.staticflickr.com/65535/51809688299_06b6a9fe69_n.jpg",
        "link_img": "https://live.staticflickr.com/65535/51809688299_4ed49879f4_o.png",
        "id_image": "copy_3056374"
      },
      {
        "link_thumb": "https://live.staticflickr.com/65535/51809688239_2239277c99_n.jpg",
        "link_img": "https://live.staticflickr.com/65535/51809688239_c3db3332f3_o.png",
        "id_image": "copy_4371362"
      }
    ],
    "hash_code_list_img": "-1561563798"
  },
  {
    "link_it": "https://github.com/lmbstudiocontact/cb_img_5000_it_2/raw/main/medication_cb_img_5000_it.json",
    "id_item": "medication_cb_img_5000_it",
    "id_album": "570943400",
    "english": "medication",
    "list_mean": [
      "cấp thuốc"
    ],
    "cau_en": "",
    "cau_vn": "",
    "hash_code_list_mean": "264723328",
    "list_img": [
      {
        "link_thumb": "https://live.staticflickr.com/65535/51809318076_83976cd71f_n.jpg",
        "link_img": "https://live.staticflickr.com/65535/51809318076_56620cf7fc_o.png",
        "id_image": "medication_1098069"
      },
      {
        "link_thumb": "https://live.staticflickr.com/65535/51809433308_26ba3f1922_n.jpg",
        "link_img": "https://live.staticflickr.com/65535/51809433308_10b88985b7_o.png",
        "id_image": "medication_2621577"
      },
      {
        "link_thumb": "https://live.staticflickr.com/65535/51809318071_55c13aca4f_n.jpg",
        "link_img": "https://live.staticflickr.com/65535/51809318071_0b8658e846_o.png",
        "id_image": "medication_2621814"
      },
      {
        "link_thumb": "https://live.staticflickr.com/65535/51809433273_1132d0aefe_n.jpg",
        "link_img": "https://live.staticflickr.com/65535/51809433273_e88bc8f6ce_o.png",
        "id_image": "medication_4514486"
      },
      {
        "link_thumb": "https://live.staticflickr.com/65535/51809672949_a996c6874b_n.jpg",
        "link_img": "https://live.staticflickr.com/65535/51809672949_b10442e854_o.png",
        "id_image": "medication_552437"
      }
    ],
    "hash_code_list_img": "1240558956"
  },
  {
    "link_it": "https://github.com/lmbstudiocontact/cb_img_5000_it_3/raw/main/property_cb_img_5000_it.json",
    "id_item": "property_cb_img_5000_it",
    "id_album": "570943400",
    "english": "property",
    "list_mean": [
      "tài sản",
      "bất động sản",
      "thuộc tính",
      "đồ dùng biểu diễn"
    ],
    "cau_en": "",
    "cau_vn": "",
    "hash_code_list_mean": "1870878413",
    "list_img": [
      {
        "link_thumb": "https://live.staticflickr.com/65535/51809465413_d3eaa63033_n.jpg",
        "link_img": "https://live.staticflickr.com/65535/51809465413_e6e77f7741_o.png",
        "id_image": "property_2590602"
      },
      {
        "link_thumb": "https://live.staticflickr.com/65535/51810088000_f98df72b90_n.jpg",
        "link_img": "https://live.staticflickr.com/65535/51810088000_09ebf297aa_o.png",
        "id_image": "property_4827587"
      },
      {
        "link_thumb": "https://live.staticflickr.com/65535/51809705384_38392604ba_n.jpg",
        "link_img": "https://live.staticflickr.com/65535/51809705384_4855c7800e_o.png",
        "id_image": "property_5928184"
      },
      {
        "link_thumb": "https://live.staticflickr.com/65535/51810087950_d495859b62_n.jpg",
        "link_img": "https://live.staticflickr.com/65535/51810087950_4734a22c8c_o.png",
        "id_image": "property_5928220"
      },
      {
        "link_thumb": "https://live.staticflickr.com/65535/51810087920_531a7f790e_n.jpg",
        "link_img": "https://live.staticflickr.com/65535/51810087920_6c22e78105_o.png",
        "id_image": "property_5928283"
      }
    ],
    "hash_code_list_img": "-632367805"
  },
  {
    "link_it": "https://github.com/lmbstudiocontact/cb_img_5000_it_0/raw/main/bolt_cb_img_5000_it.json",
    "id_item": "bolt_cb_img_5000_it",
    "id_album": "570943400",
    "english": "bolt",
    "list_mean": [
      "then cửa",
      "bu lông",
      "chớp",
      "súc vải",
      "cài then",
      "nuốt chửng",
      "lao đi"
    ],
    "cau_en": "",
    "cau_vn": "",
    "hash_code_list_mean": "-677303157",
    "list_img": [
      {
        "link_thumb": "https://live.staticflickr.com/65535/51808370312_cdb4ce24c4_n.jpg",
        "link_img": "https://live.staticflickr.com/65535/51808370312_d970ef3107_o.png",
        "id_image": "bolt_1719846"
      },
      {
        "link_thumb": "https://live.staticflickr.com/65535/51809440458_40a5c1df4a_n.jpg",
        "link_img": "https://live.staticflickr.com/65535/51809440458_f28a76b11a_o.png",
        "id_image": "bolt_1752462"
      },
      {
        "link_thumb": "https://live.staticflickr.com/65535/51809440408_11c7be1bb8_n.jpg",
        "link_img": "https://live.staticflickr.com/65535/51809440408_8446f4c7e7_o.png",
        "id_image": "bolt_3155263"
      },
      {
        "link_thumb": "https://live.staticflickr.com/65535/51809440323_284ef00dc3_n.jpg",
        "link_img": "https://live.staticflickr.com/65535/51809440323_de197ddbd9_o.png",
        "id_image": "bolt_3468393"
      },
      {
        "link_thumb": "https://live.staticflickr.com/65535/51810062085_1dac083963_n.jpg",
        "link_img": "https://live.staticflickr.com/65535/51810062085_e996596998_o.png",
        "id_image": "bolt_6196102"
      }
    ],
    "hash_code_list_img": "356480668"
  },
  {
    "link_it": "https://github.com/lmbstudiocontact/cb_img_5000_it_4/raw/main/textile_cb_img_5000_it.json",
    "id_item": "textile_cb_img_5000_it",
    "id_album": "570943400",
    "english": "textile",
    "list_mean": [
      "hàng dệt may"
    ],
    "cau_en": "",
    "cau_vn": "",
    "hash_code_list_mean": "954039014",
    "list_img": [
      {
        "link_thumb": "https://live.staticflickr.com/65535/51809465473_af1b1b77e7_n.jpg",
        "link_img": "https://live.staticflickr.com/65535/51809465473_cdb9f90dca_o.png",
        "id_image": "textile_1466542"
      },
      {
        "link_thumb": "https://live.staticflickr.com/65535/51808395627_e06b21ca27_n.jpg",
        "link_img": "https://live.staticflickr.com/65535/51808395627_0fe991b4f6_o.png",
        "id_image": "textile_2818430"
      },
      {
        "link_thumb": "https://live.staticflickr.com/65535/51809350906_42fdbf9a23_n.jpg",
        "link_img": "https://live.staticflickr.com/65535/51809350906_c1b8497218_o.png",
        "id_image": "textile_5231955"
      }
    ],
    "hash_code_list_img": "896949396"
  },
  {
    "link_it": "https://github.com/lmbstudiocontact/cb_img_5000_it_4/raw/main/side_cb_img_5000_it.json",
    "id_item": "side_cb_img_5000_it",
    "id_album": "570943400",
    "english": "side",
    "list_mean": [
      "mép, lề, bờ, ranh giới",
      "mặt",
      "cạnh, bên cạnh",
      "sườn",
      "phía, bên",
      "sườn, vách",
      "khía cạnh",
      "phe, phái",
      "phụ, ít quan trọng",
      "bờ, rìa, mép"
    ],
    "cau_en": "",
    "cau_vn": "",
    "hash_code_list_mean": "-2088024399",
    "list_img": [
      {
        "link_thumb": "https://live.staticflickr.com/65535/51809455263_a844ccc226_n.jpg",
        "link_img": "https://live.staticflickr.com/65535/51809455263_fac0d0dc7b_o.png",
        "id_image": "sideboard_1691582"
      }
    ],
    "hash_code_list_img": "723569420"
  },
  {
    "link_it": "https://github.com/lmbstudiocontact/cb_img_5000_it_1/raw/main/elegant_cb_img_5000_it.json",
    "id_item": "elegant_cb_img_5000_it",
    "id_album": "570943400",
    "english": "elegant",
    "list_mean": [
      "thanh lịch"
    ],
    "cau_en": "",
    "cau_vn": "",
    "hash_code_list_mean": "-1204584900",
    "list_img": [
      {
        "link_thumb": "https://live.staticflickr.com/65535/51808369852_fca7a3a296_n.jpg",
        "link_img": "https://live.staticflickr.com/65535/51808369852_cac1c862f9_o.png",
        "id_image": "elegant_1482343"
      },
      {
        "link_thumb": "https://live.staticflickr.com/65535/51808369747_720f0dbc9c_n.jpg",
        "link_img": "https://live.staticflickr.com/65535/51808369747_27437fd8cd_o.png",
        "id_image": "elegant_1618577"
      },
      {
        "link_thumb": "https://live.staticflickr.com/65535/51809680144_68555a0ea8_n.jpg",
        "link_img": "https://live.staticflickr.com/65535/51809680144_ba918d2e31_o.png",
        "id_image": "elegant_343857"
      }
    ],
    "hash_code_list_img": "1479481459"
  },
  {
    "link_it": "https://github.com/lmbstudiocontact/cb_img_5000_it_2/raw/main/forest_cb_img_5000_it.json",
    "id_item": "forest_cb_img_5000_it",
    "id_album": "570943400",
    "english": "forest",
    "list_mean": [
      "rừng",
      "rừng để săn bắn"
    ],
    "cau_en": "",
    "cau_vn": "",
    "hash_code_list_mean": "-1799336946",
    "list_img": [
      {
        "link_thumb": "https://live.staticflickr.com/65535/51809315481_4fd925a3a4_n.jpg",
        "link_img": "https://live.staticflickr.com/65535/51809315481_883fc581c9_o.png",
        "id_image": "forest_1151674"
      },
      {
        "link_thumb": "https://live.staticflickr.com/65535/51810051895_25645c5a8a_n.jpg",
        "link_img": "https://live.staticflickr.com/65535/51810051895_7df6d804c1_o.png",
        "id_image": "forest_1280468"
      },
      {
        "link_thumb": "https://live.staticflickr.com/65535/51810051925_a6cdc8f7c1_n.jpg",
        "link_img": "https://live.staticflickr.com/65535/51810051925_eeed3d8584_o.png",
        "id_image": "forest_172790"
      },
      {
        "link_thumb": "https://live.staticflickr.com/65535/51809670019_4312259014_n.jpg",
        "link_img": "https://live.staticflickr.com/65535/51809670019_c8eaf669f8_o.png",
        "id_image": "forest_1864084"
      }
    ],
    "hash_code_list_img": "-1246806763"
  },
  {
    "link_it": "https://github.com/lmbstudiocontact/cb_img_5000_it_0/raw/main/adaptable_cb_img_5000_it.json",
    "id_item": "adaptable_cb_img_5000_it",
    "id_album": "570943400",
    "english": "adaptable",
    "list_mean": [
      "có thể thích nghi"
    ],
    "cau_en": "",
    "cau_vn": "",
    "hash_code_list_mean": "1402503036",
    "list_img": [
      {
        "link_thumb": "https://live.staticflickr.com/65535/51809321751_a8a64aa01a_n.jpg",
        "link_img": "https://live.staticflickr.com/65535/51809321751_3cac4448c1_o.png",
        "id_image": "adaptable_4953836"
      },
      {
        "link_thumb": "https://live.staticflickr.com/65535/51809321801_6878ee6de8_n.jpg",
        "link_img": "https://live.staticflickr.com/65535/51809321801_f0ee7c8b36_o.png",
        "id_image": "adapt_6159870"
      }
    ],
    "hash_code_list_img": "539099332"
  },
  {
    "link_it": "https://github.com/lmbstudiocontact/cb_img_5000_it_4/raw/main/subway_cb_img_5000_it.json",
    "id_item": "subway_cb_img_5000_it",
    "id_album": "570943400",
    "english": "subway",
    "list_mean": [
      "đường ngầm",
      "xe điện ngầm"
    ],
    "cau_en": "",
    "cau_vn": "",
    "hash_code_list_mean": "-1556965242",
    "list_img": [
      {
        "link_thumb": "https://live.staticflickr.com/65535/51808384452_23317e6343_n.jpg",
        "link_img": "https://live.staticflickr.com/65535/51808384452_10f9ba6299_o.png",
        "id_image": "subway_224581"
      },
      {
        "link_thumb": "https://live.staticflickr.com/65535/51809339481_83eb5703c2_n.jpg",
        "link_img": "https://live.staticflickr.com/65535/51809339481_ffb89e3a12_o.png",
        "id_image": "subway_382327"
      }
    ],
    "hash_code_list_img": "444200458"
  },
  {
    "link_it": "https://github.com/lmbstudiocontact/cb_img_5000_it_2/raw/main/invisible_cb_img_5000_it.json",
    "id_item": "invisible_cb_img_5000_it",
    "id_album": "570943400",
    "english": "invisible",
    "list_mean": [
      "vô hình"
    ],
    "cau_en": "",
    "cau_vn": "",
    "hash_code_list_mean": "74678783",
    "list_img": [
      {
        "link_thumb": "https://live.staticflickr.com/65535/51809453298_6254a4e9da_n.jpg",
        "link_img": "https://live.staticflickr.com/65535/51809453298_85e47ea68e_o.png",
        "id_image": "invisible_1850043"
      },
      {
        "link_thumb": "https://live.staticflickr.com/65535/51809693504_c6d2a5edb4_n.jpg",
        "link_img": "https://live.staticflickr.com/65535/51809693504_6335a8817f_o.png",
        "id_image": "invisible_2472333"
      },
      {
        "link_thumb": "https://live.staticflickr.com/65535/51809338256_64cc6d2fb4_n.jpg",
        "link_img": "https://live.staticflickr.com/65535/51809338256_be962b25c7_o.png",
        "id_image": "invisible_5039310"
      },
      {
        "link_thumb": "https://live.staticflickr.com/65535/51809338211_023824d76c_n.jpg",
        "link_img": "https://live.staticflickr.com/65535/51809338211_ee01dbbb32_o.png",
        "id_image": "invisible_5884424"
      }
    ],
    "hash_code_list_img": "-106176614"
  },
  {
    "link_it": "https://github.com/lmbstudiocontact/cb_img_5000_it_5/raw/main/videotape_cb_img_5000_it.json",
    "id_item": "videotape_cb_img_5000_it",
    "id_album": "570943400",
    "english": "videotape",
    "list_mean": [
      "băng viđêô",
      "thâu vào băng viđêô"
    ],
    "cau_en": "",
    "cau_vn": "",
    "hash_code_list_mean": "408104053",
    "list_img": [
      {
        "link_thumb": "https://live.staticflickr.com/65535/51809344651_171cf6daf5_n.jpg",
        "link_img": "https://live.staticflickr.com/65535/51809344651_1996001784_o.png",
        "id_image": "videotape_2621279"
      },
      {
        "link_thumb": "https://live.staticflickr.com/65535/51809459418_595671d0d3_n.jpg",
        "link_img": "https://live.staticflickr.com/65535/51809459418_affab0d1dc_o.png",
        "id_image": "videotape_3172558"
      },
      {
        "link_thumb": "https://live.staticflickr.com/65535/51809699679_e530fbd12e_n.jpg",
        "link_img": "https://live.staticflickr.com/65535/51809699679_c75bed08ab_o.png",
        "id_image": "videotape_4028458"
      },
      {
        "link_thumb": "https://live.staticflickr.com/65535/51809459353_f63a1e624c_n.jpg",
        "link_img": "https://live.staticflickr.com/65535/51809459353_9ea112659a_o.png",
        "id_image": "videotape_4321497"
      }
    ],
    "hash_code_list_img": "-1423418290"
  },
  {
    "link_it": "https://github.com/lmbstudiocontact/cb_img_5000_it_5/raw/main/veteran_cb_img_5000_it.json",
    "id_item": "veteran_cb_img_5000_it",
    "id_album": "570943400",
    "english": "veteran",
    "list_mean": [
      "người kỳ cựu",
      "cựu chiến binh"
    ],
    "cau_en": "",
    "cau_vn": "",
    "hash_code_list_mean": "-304876676",
    "list_img": [
      {
        "link_thumb": "https://live.staticflickr.com/65535/51809460238_6da0657f95_n.jpg",
        "link_img": "https://live.staticflickr.com/65535/51809460238_9937ffa1f4_o.png",
        "id_image": "veteran_2142618"
      },
      {
        "link_thumb": "https://live.staticflickr.com/65535/51809700564_3133cd1038_n.jpg",
        "link_img": "https://live.staticflickr.com/65535/51809700564_462e28504b_o.png",
        "id_image": "veteran_4850575"
      }
    ],
    "hash_code_list_img": "-1212898134"
  },
  {
    "link_it": "https://github.com/lmbstudiocontact/cb_img_5000_it_1/raw/main/demon_cb_img_5000_it.json",
    "id_item": "demon_cb_img_5000_it",
    "id_album": "570943400",
    "english": "demon",
    "list_mean": [
      "ma quỷ"
    ],
    "cau_en": "",
    "cau_vn": "",
    "hash_code_list_mean": "-1083734810",
    "list_img": [
      {
        "link_thumb": "https://live.staticflickr.com/65535/51809448043_ecc9c46aca_n.jpg",
        "link_img": "https://live.staticflickr.com/65535/51809448043_ae982a49fb_o.png",
        "id_image": "demon_3539370"
      },
      {
        "link_thumb": "https://live.staticflickr.com/65535/51809687944_761bd6bc8e_n.jpg",
        "link_img": "https://live.staticflickr.com/65535/51809687944_eea9448f29_o.png",
        "id_image": "demon_5252737"
      },
      {
        "link_thumb": "https://live.staticflickr.com/65535/51809448078_c76110cce3_n.jpg",
        "link_img": "https://live.staticflickr.com/65535/51809448078_ed6d3a44ec_o.png",
        "id_image": "demon_606875"
      }
    ],
    "hash_code_list_img": "-1506082228"
  },
  {
    "link_it": "https://github.com/lmbstudiocontact/cb_img_5000_it_0/raw/main/autonomous_cb_img_5000_it.json",
    "id_item": "autonomous_cb_img_5000_it",
    "id_album": "570943400",
    "english": "autonomous",
    "list_mean": [
      "tự trị"
    ],
    "cau_en": "",
    "cau_vn": "",
    "hash_code_list_mean": "2047333001",
    "list_img": [
      {
        "link_thumb": "https://live.staticflickr.com/65535/51808369752_3f89da860b_n.jpg",
        "link_img": "https://live.staticflickr.com/65535/51808369752_0acb08bf9a_o.png",
        "id_image": "autonomous_2080825"
      },
      {
        "link_thumb": "https://live.staticflickr.com/65535/51809324881_132510cb20_n.jpg",
        "link_img": "https://live.staticflickr.com/65535/51809324881_4da4281e69_o.png",
        "id_image": "autonomous_5901702"
      }
    ],
    "hash_code_list_img": "546933389"
  },
  {
    "link_it": "https://github.com/lmbstudiocontact/cb_img_5000_it_0/raw/main/autumn_cb_img_5000_it.json",
    "id_item": "autumn_cb_img_5000_it",
    "id_album": "570943400",
    "english": "autumn",
    "list_mean": [
      "mùa thu"
    ],
    "cau_en": "",
    "cau_vn": "",
    "hash_code_list_mean": "877994421",
    "list_img": [
      {
        "link_thumb": "https://live.staticflickr.com/65535/51809439788_64bfd4c31a_n.jpg",
        "link_img": "https://live.staticflickr.com/65535/51809439788_fb75c9300a_o.png",
        "id_image": "autumn_2153158"
      },
      {
        "link_thumb": "https://live.staticflickr.com/65535/51809439763_1131df7d14_n.jpg",
        "link_img": "https://live.staticflickr.com/65535/51809439763_7940011948_o.png",
        "id_image": "autumn_4968404"
      },
      {
        "link_thumb": "https://live.staticflickr.com/65535/51810061550_7070a9c628_n.jpg",
        "link_img": "https://live.staticflickr.com/65535/51810061550_4d2effee1c_o.png",
        "id_image": "autumn_5265609"
      },
      {
        "link_thumb": "https://live.staticflickr.com/65535/51809679814_e721000b58_n.jpg",
        "link_img": "https://live.staticflickr.com/65535/51809679814_d177683c45_o.png",
        "id_image": "autumn_5392259"
      }
    ],
    "hash_code_list_img": "1593595137"
  },
  {
    "link_it": "https://github.com/lmbstudiocontact/cb_img_5000_it_2/raw/main/line_cb_img_5000_it.json",
    "id_item": "line_cb_img_5000_it",
    "id_album": "570943400",
    "english": "line",
    "list_mean": [
      "dây",
      "đường kẻ",
      "đường nét",
      "nếp nhăn",
      "xếp hàng",
      "vài dòng",
      "dòng họ",
      "hướng",
      "đường tàu hỏa",
      "đường dây",
      "dòng chữ",
      "tuyến đường",
      "chuyên ngành",
      "phòng tuyến",
      "xếp thành hàng dọc",
      "đánh dấu",
      "phủ bên trong",
      "lót"
    ],
    "cau_en": "",
    "cau_vn": "",
    "hash_code_list_mean": "-913040380",
    "list_img": [
      {
        "link_thumb": "https://live.staticflickr.com/65535/51810078770_92d7f6c929_n.jpg",
        "link_img": "https://live.staticflickr.com/65535/51810078770_709925f72b_o.png",
        "id_image": "line_168653"
      },
      {
        "link_thumb": "https://live.staticflickr.com/65535/51810078725_31333847a3_n.jpg",
        "link_img": "https://live.staticflickr.com/65535/51810078725_6298e26af0_o.png",
        "id_image": "line_207014"
      }
    ],
    "hash_code_list_img": "-2034240653"
  },
  {
    "link_it": "https://github.com/lmbstudiocontact/cb_img_5000_it_3/raw/main/primer_cb_img_5000_it.json",
    "id_item": "primer_cb_img_5000_it",
    "id_album": "570943400",
    "english": "primer",
    "list_mean": [
      "sách giới thiệu",
      "lớp sơn lót"
    ],
    "cau_en": "",
    "cau_vn": "",
    "hash_code_list_mean": "1316775247",
    "list_img": [
      {
        "link_thumb": "https://live.staticflickr.com/65535/51809680844_d4afed3772_n.jpg",
        "link_img": "https://live.staticflickr.com/65535/51809680844_e78f5c3362_o.png",
        "id_image": "primer_2286607"
      },
      {
        "link_thumb": "https://live.staticflickr.com/65535/51810062500_e75938e7aa_n.jpg",
        "link_img": "https://live.staticflickr.com/65535/51810062500_1ae38a1a6f_o.png",
        "id_image": "primer_6075366"
      }
    ],
    "hash_code_list_img": "-1923236261"
  }
]